<?xml version="1.0" encoding="utf-8"?>
<!-- Lightroom definition file. -->
<lightroom>
    <size x="100" y="100" z="66" cellsize="2" />
    <hemigrid size="5" latitude="36.48" diffus="0.5" />
    <cutvalue>0.05</cutvalue>
    <!-- possible values for cuttoffMode: sum (percentage of sum of values), north (absolute value in north direction) -->
    <cutoffMode>north</cutoffMode> 
    <aggregationMode>mean</aggregationMode>
	<readerStamp>C:\Users\kible\Documents\Research\iLand\SEKI_data\pipo_reader_v2.bin</readerStamp>
	<outputStamp>C:\Users\kible\Documents\Research\iLand\SEKI_data\pipo_out_v2.bin</outputStamp>
    <desc>Pinus ponderosa for Sequoia National Park (latitude from CIRQUE).</desc>
    <trees>
	<tree name="pipo_1_0.45" bhd="1" h="0.45" crown="0.18" formula="1.381*(min(0.95, hrel)/0.95)^0.29491"/>
	<tree name="pipo_1_0.55" bhd="1" h="0.55" crown="0.22" formula="1.381*(min(0.95, hrel)/0.95)^0.29491"/>
	<tree name="pipo_1_0.65" bhd="1" h="0.65" crown="0.26" formula="1.381*(min(0.95, hrel)/0.95)^0.29491"/>
	<tree name="pipo_1_0.75" bhd="1" h="0.75" crown="0.3" formula="1.381*(min(0.95, hrel)/0.95)^0.29491"/>
	<tree name="pipo_1_0.85" bhd="1" h="0.85" crown="0.33" formula="1.381*(min(0.95, hrel)/0.95)^0.29491"/>
	<tree name="pipo_1_0.95" bhd="1" h="0.95" crown="0.37" formula="1.381*(min(0.95, hrel)/0.95)^0.29491"/>
	<tree name="pipo_1_1.05" bhd="1" h="1.05" crown="0.41" formula="1.381*(min(0.95, hrel)/0.95)^0.29491"/>
	<tree name="pipo_1_1.15" bhd="1" h="1.15" crown="0.45" formula="1.381*(min(0.95, hrel)/0.95)^0.29491"/>
	<tree name="pipo_1_1.25" bhd="1" h="1.25" crown="0.49" formula="1.381*(min(0.95, hrel)/0.95)^0.29491"/>
	<tree name="pipo_1_1.35" bhd="1" h="1.35" crown="0.53" formula="1.381*(min(0.95, hrel)/0.95)^0.29491"/>
	<tree name="pipo_1_1.45" bhd="1" h="1.45" crown="0.57" formula="1.381*(min(0.95, hrel)/0.95)^0.29491"/>
	<tree name="pipo_1_1.55" bhd="1" h="1.55" crown="0.61" formula="1.381*(min(0.95, hrel)/0.95)^0.29491"/>
	<tree name="pipo_1_1.65" bhd="1" h="1.65" crown="0.65" formula="1.381*(min(0.95, hrel)/0.95)^0.29491"/>
	<tree name="pipo_1_1.75" bhd="1" h="1.75" crown="0.69" formula="1.381*(min(0.95, hrel)/0.95)^0.29491"/>
	<tree name="pipo_1_1.85" bhd="1" h="1.85" crown="0.73" formula="1.381*(min(0.95, hrel)/0.95)^0.29491"/>
	<tree name="pipo_2_0.9" bhd="2" h="0.9" crown="0.35" formula="1.434*(min(0.95, hrel)/0.95)^0.29491"/>
	<tree name="pipo_2_1.1" bhd="2" h="1.1" crown="0.43" formula="1.434*(min(0.95, hrel)/0.95)^0.29491"/>
	<tree name="pipo_2_1.3" bhd="2" h="1.3" crown="0.51" formula="1.434*(min(0.95, hrel)/0.95)^0.29491"/>
	<tree name="pipo_2_1.5" bhd="2" h="1.5" crown="0.59" formula="1.434*(min(0.95, hrel)/0.95)^0.29491"/>
	<tree name="pipo_2_1.7" bhd="2" h="1.7" crown="0.67" formula="1.434*(min(0.95, hrel)/0.95)^0.29491"/>
	<tree name="pipo_2_1.9" bhd="2" h="1.9" crown="0.75" formula="1.434*(min(0.95, hrel)/0.95)^0.29491"/>
	<tree name="pipo_2_2.1" bhd="2" h="2.1" crown="0.83" formula="1.434*(min(0.95, hrel)/0.95)^0.29491"/>
	<tree name="pipo_2_2.3" bhd="2" h="2.3" crown="0.91" formula="1.434*(min(0.95, hrel)/0.95)^0.29491"/>
	<tree name="pipo_2_2.5" bhd="2" h="2.5" crown="0.99" formula="1.434*(min(0.95, hrel)/0.95)^0.29491"/>
	<tree name="pipo_2_2.7" bhd="2" h="2.7" crown="1.06" formula="1.434*(min(0.95, hrel)/0.95)^0.29491"/>
	<tree name="pipo_2_2.9" bhd="2" h="2.9" crown="1.14" formula="1.434*(min(0.95, hrel)/0.95)^0.29491"/>
	<tree name="pipo_2_3.1" bhd="2" h="3.1" crown="1.22" formula="1.434*(min(0.95, hrel)/0.95)^0.29491"/>
	<tree name="pipo_2_3.3" bhd="2" h="3.3" crown="1.3" formula="1.434*(min(0.95, hrel)/0.95)^0.29491"/>
	<tree name="pipo_3_1.35" bhd="3" h="1.35" crown="0.53" formula="1.488*(min(0.95, hrel)/0.95)^0.29491"/>
	<tree name="pipo_3_1.65" bhd="3" h="1.65" crown="0.65" formula="1.488*(min(0.95, hrel)/0.95)^0.29491"/>
	<tree name="pipo_3_1.95" bhd="3" h="1.95" crown="0.77" formula="1.488*(min(0.95, hrel)/0.95)^0.29491"/>
	<tree name="pipo_3_2.25" bhd="3" h="2.25" crown="0.89" formula="1.488*(min(0.95, hrel)/0.95)^0.29491"/>
	<tree name="pipo_3_2.55" bhd="3" h="2.55" crown="1" formula="1.488*(min(0.95, hrel)/0.95)^0.29491"/>
	<tree name="pipo_3_2.85" bhd="3" h="2.85" crown="1.12" formula="1.488*(min(0.95, hrel)/0.95)^0.29491"/>
	<tree name="pipo_3_3.15" bhd="3" h="3.15" crown="1.24" formula="1.488*(min(0.95, hrel)/0.95)^0.29491"/>
	<tree name="pipo_3_3.45" bhd="3" h="3.45" crown="1.36" formula="1.488*(min(0.95, hrel)/0.95)^0.29491"/>
	<tree name="pipo_3_3.75" bhd="3" h="3.75" crown="1.48" formula="1.488*(min(0.95, hrel)/0.95)^0.29491"/>
	<tree name="pipo_3_4.05" bhd="3" h="4.05" crown="1.6" formula="1.488*(min(0.95, hrel)/0.95)^0.29491"/>
	<tree name="pipo_3_4.35" bhd="3" h="4.35" crown="1.71" formula="1.488*(min(0.95, hrel)/0.95)^0.29491"/>
	<tree name="pipo_3_4.65" bhd="3" h="4.65" crown="1.83" formula="1.488*(min(0.95, hrel)/0.95)^0.29491"/>
	<tree name="pipo_4_1.8" bhd="4" h="1.8" crown="0.71" formula="1.542*(min(0.95, hrel)/0.95)^0.29491"/>
	<tree name="pipo_4_2.2" bhd="4" h="2.2" crown="0.87" formula="1.542*(min(0.95, hrel)/0.95)^0.29491"/>
	<tree name="pipo_4_2.6" bhd="4" h="2.6" crown="1.02" formula="1.542*(min(0.95, hrel)/0.95)^0.29491"/>
	<tree name="pipo_4_3" bhd="4" h="3" crown="1.18" formula="1.542*(min(0.95, hrel)/0.95)^0.29491"/>
	<tree name="pipo_4_3.4" bhd="4" h="3.4" crown="1.34" formula="1.542*(min(0.95, hrel)/0.95)^0.29491"/>
	<tree name="pipo_4_3.8" bhd="4" h="3.8" crown="1.5" formula="1.542*(min(0.95, hrel)/0.95)^0.29491"/>
	<tree name="pipo_4_4.2" bhd="4" h="4.2" crown="1.65" formula="1.542*(min(0.95, hrel)/0.95)^0.29491"/>
	<tree name="pipo_4_4.6" bhd="4" h="4.6" crown="1.81" formula="1.542*(min(0.95, hrel)/0.95)^0.29491"/>
	<tree name="pipo_4_5" bhd="4" h="5" crown="1.97" formula="1.542*(min(0.95, hrel)/0.95)^0.29491"/>
	<tree name="pipo_4_5.4" bhd="4" h="5.4" crown="2.13" formula="1.542*(min(0.95, hrel)/0.95)^0.29491"/>
	<tree name="pipo_4_5.8" bhd="4" h="5.8" crown="2.29" formula="1.542*(min(0.95, hrel)/0.95)^0.29491"/>
	<tree name="pipo_5_2.25" bhd="5" h="2.25" crown="0.89" formula="1.596*(min(0.95, hrel)/0.95)^0.29491"/>
	<tree name="pipo_5_2.75" bhd="5" h="2.75" crown="1.08" formula="1.596*(min(0.95, hrel)/0.95)^0.29491"/>
	<tree name="pipo_5_3.25" bhd="5" h="3.25" crown="1.28" formula="1.596*(min(0.95, hrel)/0.95)^0.29491"/>
	<tree name="pipo_5_3.75" bhd="5" h="3.75" crown="1.48" formula="1.596*(min(0.95, hrel)/0.95)^0.29491"/>
	<tree name="pipo_5_4.25" bhd="5" h="4.25" crown="1.67" formula="1.596*(min(0.95, hrel)/0.95)^0.29491"/>
	<tree name="pipo_5_4.75" bhd="5" h="4.75" crown="1.87" formula="1.596*(min(0.95, hrel)/0.95)^0.29491"/>
	<tree name="pipo_5_5.25" bhd="5" h="5.25" crown="2.07" formula="1.596*(min(0.95, hrel)/0.95)^0.29491"/>
	<tree name="pipo_5_5.75" bhd="5" h="5.75" crown="2.27" formula="1.596*(min(0.95, hrel)/0.95)^0.29491"/>
	<tree name="pipo_5_6.25" bhd="5" h="6.25" crown="2.46" formula="1.596*(min(0.95, hrel)/0.95)^0.29491"/>
	<tree name="pipo_5_6.75" bhd="5" h="6.75" crown="2.66" formula="1.596*(min(0.95, hrel)/0.95)^0.29491"/>
	<tree name="pipo_6_2.7" bhd="6" h="2.7" crown="1.06" formula="1.65*(min(0.95, hrel)/0.95)^0.29491"/>
	<tree name="pipo_6_3.3" bhd="6" h="3.3" crown="1.3" formula="1.65*(min(0.95, hrel)/0.95)^0.29491"/>
	<tree name="pipo_6_3.9" bhd="6" h="3.9" crown="1.54" formula="1.65*(min(0.95, hrel)/0.95)^0.29491"/>
	<tree name="pipo_6_4.5" bhd="6" h="4.5" crown="1.77" formula="1.65*(min(0.95, hrel)/0.95)^0.29491"/>
	<tree name="pipo_6_5.1" bhd="6" h="5.1" crown="2.01" formula="1.65*(min(0.95, hrel)/0.95)^0.29491"/>
	<tree name="pipo_6_5.7" bhd="6" h="5.7" crown="2.25" formula="1.65*(min(0.95, hrel)/0.95)^0.29491"/>
	<tree name="pipo_6_6.3" bhd="6" h="6.3" crown="2.48" formula="1.65*(min(0.95, hrel)/0.95)^0.29491"/>
	<tree name="pipo_6_6.9" bhd="6" h="6.9" crown="2.72" formula="1.65*(min(0.95, hrel)/0.95)^0.29491"/>
	<tree name="pipo_6_7.5" bhd="6" h="7.5" crown="2.96" formula="1.65*(min(0.95, hrel)/0.95)^0.29491"/>
	<tree name="pipo_6_8.1" bhd="6" h="8.1" crown="3.19" formula="1.65*(min(0.95, hrel)/0.95)^0.29491"/>
	<tree name="pipo_7_3.15" bhd="7" h="3.15" crown="1.24" formula="1.704*(min(0.95, hrel)/0.95)^0.29491"/>
	<tree name="pipo_7_3.85" bhd="7" h="3.85" crown="1.52" formula="1.704*(min(0.95, hrel)/0.95)^0.29491"/>
	<tree name="pipo_7_4.55" bhd="7" h="4.55" crown="1.79" formula="1.704*(min(0.95, hrel)/0.95)^0.29491"/>
	<tree name="pipo_7_5.25" bhd="7" h="5.25" crown="2.07" formula="1.704*(min(0.95, hrel)/0.95)^0.29491"/>
	<tree name="pipo_7_5.95" bhd="7" h="5.95" crown="2.34" formula="1.704*(min(0.95, hrel)/0.95)^0.29491"/>
	<tree name="pipo_7_6.65" bhd="7" h="6.65" crown="2.62" formula="1.704*(min(0.95, hrel)/0.95)^0.29491"/>
	<tree name="pipo_7_7.35" bhd="7" h="7.35" crown="2.9" formula="1.704*(min(0.95, hrel)/0.95)^0.29491"/>
	<tree name="pipo_7_8.05" bhd="7" h="8.05" crown="3.17" formula="1.704*(min(0.95, hrel)/0.95)^0.29491"/>
	<tree name="pipo_7_8.75" bhd="7" h="8.75" crown="3.45" formula="1.704*(min(0.95, hrel)/0.95)^0.29491"/>
	<tree name="pipo_8_3.6" bhd="8" h="3.6" crown="1.42" formula="1.758*(min(0.95, hrel)/0.95)^0.29491"/>
	<tree name="pipo_8_4.4" bhd="8" h="4.4" crown="1.73" formula="1.758*(min(0.95, hrel)/0.95)^0.29491"/>
	<tree name="pipo_8_5.2" bhd="8" h="5.2" crown="2.05" formula="1.758*(min(0.95, hrel)/0.95)^0.29491"/>
	<tree name="pipo_8_6" bhd="8" h="6" crown="2.36" formula="1.758*(min(0.95, hrel)/0.95)^0.29491"/>
	<tree name="pipo_8_6.8" bhd="8" h="6.8" crown="2.68" formula="1.758*(min(0.95, hrel)/0.95)^0.29491"/>
	<tree name="pipo_8_7.6" bhd="8" h="7.6" crown="2.99" formula="1.758*(min(0.95, hrel)/0.95)^0.29491"/>
	<tree name="pipo_8_8.4" bhd="8" h="8.4" crown="3.31" formula="1.758*(min(0.95, hrel)/0.95)^0.29491"/>
	<tree name="pipo_8_9.2" bhd="8" h="9.2" crown="3.62" formula="1.758*(min(0.95, hrel)/0.95)^0.29491"/>
	<tree name="pipo_8_10" bhd="8" h="10" crown="3.94" formula="1.758*(min(0.95, hrel)/0.95)^0.29491"/>
	<tree name="pipo_9_4.05" bhd="9" h="4.05" crown="1.6" formula="1.812*(min(0.95, hrel)/0.95)^0.29491"/>
	<tree name="pipo_9_4.95" bhd="9" h="4.95" crown="1.95" formula="1.812*(min(0.95, hrel)/0.95)^0.29491"/>
	<tree name="pipo_9_5.85" bhd="9" h="5.85" crown="2.3" formula="1.812*(min(0.95, hrel)/0.95)^0.29491"/>
	<tree name="pipo_9_6.75" bhd="9" h="6.75" crown="2.66" formula="1.812*(min(0.95, hrel)/0.95)^0.29491"/>
	<tree name="pipo_9_7.65" bhd="9" h="7.65" crown="3.01" formula="1.812*(min(0.95, hrel)/0.95)^0.29491"/>
	<tree name="pipo_9_8.55" bhd="9" h="8.55" crown="3.37" formula="1.812*(min(0.95, hrel)/0.95)^0.29491"/>
	<tree name="pipo_9_9.45" bhd="9" h="9.45" crown="3.72" formula="1.812*(min(0.95, hrel)/0.95)^0.29491"/>
	<tree name="pipo_9_10.35" bhd="9" h="10.35" crown="4.08" formula="1.812*(min(0.95, hrel)/0.95)^0.29491"/>
	<tree name="pipo_9_11.25" bhd="9" h="11.25" crown="4.43" formula="1.812*(min(0.95, hrel)/0.95)^0.29491"/>
	<tree name="pipo_10_4.5" bhd="10" h="4.5" crown="1.77" formula="1.866*(min(0.95, hrel)/0.95)^0.29491"/>
	<tree name="pipo_10_5.5" bhd="10" h="5.5" crown="2.17" formula="1.866*(min(0.95, hrel)/0.95)^0.29491"/>
	<tree name="pipo_10_6.5" bhd="10" h="6.5" crown="2.56" formula="1.866*(min(0.95, hrel)/0.95)^0.29491"/>
	<tree name="pipo_10_7.5" bhd="10" h="7.5" crown="2.96" formula="1.866*(min(0.95, hrel)/0.95)^0.29491"/>
	<tree name="pipo_10_8.5" bhd="10" h="8.5" crown="3.35" formula="1.866*(min(0.95, hrel)/0.95)^0.29491"/>
	<tree name="pipo_10_9.5" bhd="10" h="9.5" crown="3.74" formula="1.866*(min(0.95, hrel)/0.95)^0.29491"/>
	<tree name="pipo_10_10.5" bhd="10" h="10.5" crown="4.14" formula="1.866*(min(0.95, hrel)/0.95)^0.29491"/>
	<tree name="pipo_10_11.5" bhd="10" h="11.5" crown="4.53" formula="1.866*(min(0.95, hrel)/0.95)^0.29491"/>
	<tree name="pipo_11_4.95" bhd="11" h="4.95" crown="1.95" formula="1.92*(min(0.95, hrel)/0.95)^0.29491"/>
	<tree name="pipo_11_6.05" bhd="11" h="6.05" crown="2.38" formula="1.92*(min(0.95, hrel)/0.95)^0.29491"/>
	<tree name="pipo_11_7.15" bhd="11" h="7.15" crown="2.82" formula="1.92*(min(0.95, hrel)/0.95)^0.29491"/>
	<tree name="pipo_11_8.25" bhd="11" h="8.25" crown="3.25" formula="1.92*(min(0.95, hrel)/0.95)^0.29491"/>
	<tree name="pipo_11_9.35" bhd="11" h="9.35" crown="3.68" formula="1.92*(min(0.95, hrel)/0.95)^0.29491"/>
	<tree name="pipo_11_10.45" bhd="11" h="10.45" crown="4.12" formula="1.92*(min(0.95, hrel)/0.95)^0.29491"/>
	<tree name="pipo_11_11.55" bhd="11" h="11.55" crown="4.55" formula="1.92*(min(0.95, hrel)/0.95)^0.29491"/>
	<tree name="pipo_11_12.65" bhd="11" h="12.65" crown="4.98" formula="1.92*(min(0.95, hrel)/0.95)^0.29491"/>
	<tree name="pipo_12_5.4" bhd="12" h="5.4" crown="2.13" formula="1.974*(min(0.95, hrel)/0.95)^0.29491"/>
	<tree name="pipo_12_6.6" bhd="12" h="6.6" crown="2.6" formula="1.974*(min(0.95, hrel)/0.95)^0.29491"/>
	<tree name="pipo_12_7.8" bhd="12" h="7.8" crown="3.07" formula="1.974*(min(0.95, hrel)/0.95)^0.29491"/>
	<tree name="pipo_12_9" bhd="12" h="9" crown="3.55" formula="1.974*(min(0.95, hrel)/0.95)^0.29491"/>
	<tree name="pipo_12_10.2" bhd="12" h="10.2" crown="4.02" formula="1.974*(min(0.95, hrel)/0.95)^0.29491"/>
	<tree name="pipo_12_11.4" bhd="12" h="11.4" crown="4.49" formula="1.974*(min(0.95, hrel)/0.95)^0.29491"/>
	<tree name="pipo_12_12.6" bhd="12" h="12.6" crown="4.96" formula="1.974*(min(0.95, hrel)/0.95)^0.29491"/>
	<tree name="pipo_12_13.8" bhd="12" h="13.8" crown="5.44" formula="1.974*(min(0.95, hrel)/0.95)^0.29491"/>
	<tree name="pipo_13_5.85" bhd="13" h="5.85" crown="2.3" formula="2.027*(min(0.95, hrel)/0.95)^0.29491"/>
	<tree name="pipo_13_7.15" bhd="13" h="7.15" crown="2.82" formula="2.027*(min(0.95, hrel)/0.95)^0.29491"/>
	<tree name="pipo_13_8.45" bhd="13" h="8.45" crown="3.33" formula="2.027*(min(0.95, hrel)/0.95)^0.29491"/>
	<tree name="pipo_13_9.75" bhd="13" h="9.75" crown="3.84" formula="2.027*(min(0.95, hrel)/0.95)^0.29491"/>
	<tree name="pipo_13_11.05" bhd="13" h="11.05" crown="4.35" formula="2.027*(min(0.95, hrel)/0.95)^0.29491"/>
	<tree name="pipo_13_12.35" bhd="13" h="12.35" crown="4.87" formula="2.027*(min(0.95, hrel)/0.95)^0.29491"/>
	<tree name="pipo_13_13.65" bhd="13" h="13.65" crown="5.38" formula="2.027*(min(0.95, hrel)/0.95)^0.29491"/>
	<tree name="pipo_13_14.95" bhd="13" h="14.95" crown="5.89" formula="2.027*(min(0.95, hrel)/0.95)^0.29491"/>
	<tree name="pipo_14_6.3" bhd="14" h="6.3" crown="2.48" formula="2.081*(min(0.95, hrel)/0.95)^0.29491"/>
	<tree name="pipo_14_7.7" bhd="14" h="7.7" crown="3.03" formula="2.081*(min(0.95, hrel)/0.95)^0.29491"/>
	<tree name="pipo_14_9.1" bhd="14" h="9.1" crown="3.59" formula="2.081*(min(0.95, hrel)/0.95)^0.29491"/>
	<tree name="pipo_14_10.5" bhd="14" h="10.5" crown="4.14" formula="2.081*(min(0.95, hrel)/0.95)^0.29491"/>
	<tree name="pipo_14_11.9" bhd="14" h="11.9" crown="4.69" formula="2.081*(min(0.95, hrel)/0.95)^0.29491"/>
	<tree name="pipo_14_13.3" bhd="14" h="13.3" crown="5.24" formula="2.081*(min(0.95, hrel)/0.95)^0.29491"/>
	<tree name="pipo_14_14.7" bhd="14" h="14.7" crown="5.79" formula="2.081*(min(0.95, hrel)/0.95)^0.29491"/>
	<tree name="pipo_14_16.1" bhd="14" h="16.1" crown="6.34" formula="2.081*(min(0.95, hrel)/0.95)^0.29491"/>
	<tree name="pipo_15_6.75" bhd="15" h="6.75" crown="2.66" formula="2.135*(min(0.95, hrel)/0.95)^0.29491"/>
	<tree name="pipo_15_8.25" bhd="15" h="8.25" crown="3.25" formula="2.135*(min(0.95, hrel)/0.95)^0.29491"/>
	<tree name="pipo_15_9.75" bhd="15" h="9.75" crown="3.84" formula="2.135*(min(0.95, hrel)/0.95)^0.29491"/>
	<tree name="pipo_15_11.25" bhd="15" h="11.25" crown="4.43" formula="2.135*(min(0.95, hrel)/0.95)^0.29491"/>
	<tree name="pipo_15_12.75" bhd="15" h="12.75" crown="5.02" formula="2.135*(min(0.95, hrel)/0.95)^0.29491"/>
	<tree name="pipo_15_14.25" bhd="15" h="14.25" crown="5.61" formula="2.135*(min(0.95, hrel)/0.95)^0.29491"/>
	<tree name="pipo_15_15.75" bhd="15" h="15.75" crown="6.21" formula="2.135*(min(0.95, hrel)/0.95)^0.29491"/>
	<tree name="pipo_16_7.2" bhd="16" h="7.2" crown="2.84" formula="2.189*(min(0.95, hrel)/0.95)^0.29491"/>
	<tree name="pipo_16_8.8" bhd="16" h="8.8" crown="3.47" formula="2.189*(min(0.95, hrel)/0.95)^0.29491"/>
	<tree name="pipo_16_10.4" bhd="16" h="10.4" crown="4.1" formula="2.189*(min(0.95, hrel)/0.95)^0.29491"/>
	<tree name="pipo_16_12" bhd="16" h="12" crown="4.73" formula="2.189*(min(0.95, hrel)/0.95)^0.29491"/>
	<tree name="pipo_16_13.6" bhd="16" h="13.6" crown="5.36" formula="2.189*(min(0.95, hrel)/0.95)^0.29491"/>
	<tree name="pipo_16_15.2" bhd="16" h="15.2" crown="5.99" formula="2.189*(min(0.95, hrel)/0.95)^0.29491"/>
	<tree name="pipo_16_16.8" bhd="16" h="16.8" crown="6.62" formula="2.189*(min(0.95, hrel)/0.95)^0.29491"/>
	<tree name="pipo_17_7.65" bhd="17" h="7.65" crown="3.01" formula="2.243*(min(0.95, hrel)/0.95)^0.29491"/>
	<tree name="pipo_17_9.35" bhd="17" h="9.35" crown="3.68" formula="2.243*(min(0.95, hrel)/0.95)^0.29491"/>
	<tree name="pipo_17_11.05" bhd="17" h="11.05" crown="4.35" formula="2.243*(min(0.95, hrel)/0.95)^0.29491"/>
	<tree name="pipo_17_12.75" bhd="17" h="12.75" crown="5.02" formula="2.243*(min(0.95, hrel)/0.95)^0.29491"/>
	<tree name="pipo_17_14.45" bhd="17" h="14.45" crown="5.69" formula="2.243*(min(0.95, hrel)/0.95)^0.29491"/>
	<tree name="pipo_17_16.15" bhd="17" h="16.15" crown="6.36" formula="2.243*(min(0.95, hrel)/0.95)^0.29491"/>
	<tree name="pipo_17_17.85" bhd="17" h="17.85" crown="7.03" formula="2.243*(min(0.95, hrel)/0.95)^0.29491"/>
	<tree name="pipo_18_8.1" bhd="18" h="8.1" crown="3.19" formula="2.297*(min(0.95, hrel)/0.95)^0.29491"/>
	<tree name="pipo_18_9.9" bhd="18" h="9.9" crown="3.9" formula="2.297*(min(0.95, hrel)/0.95)^0.29491"/>
	<tree name="pipo_18_11.7" bhd="18" h="11.7" crown="4.61" formula="2.297*(min(0.95, hrel)/0.95)^0.29491"/>
	<tree name="pipo_18_13.5" bhd="18" h="13.5" crown="5.32" formula="2.297*(min(0.95, hrel)/0.95)^0.29491"/>
	<tree name="pipo_18_15.3" bhd="18" h="15.3" crown="6.03" formula="2.297*(min(0.95, hrel)/0.95)^0.29491"/>
	<tree name="pipo_18_17.1" bhd="18" h="17.1" crown="6.74" formula="2.297*(min(0.95, hrel)/0.95)^0.29491"/>
	<tree name="pipo_18_18.9" bhd="18" h="18.9" crown="7.45" formula="2.297*(min(0.95, hrel)/0.95)^0.29491"/>
	<tree name="pipo_19_8.55" bhd="19" h="8.55" crown="3.37" formula="2.351*(min(0.95, hrel)/0.95)^0.29491"/>
	<tree name="pipo_19_10.45" bhd="19" h="10.45" crown="4.12" formula="2.351*(min(0.95, hrel)/0.95)^0.29491"/>
	<tree name="pipo_19_12.35" bhd="19" h="12.35" crown="4.87" formula="2.351*(min(0.95, hrel)/0.95)^0.29491"/>
	<tree name="pipo_19_14.25" bhd="19" h="14.25" crown="5.61" formula="2.351*(min(0.95, hrel)/0.95)^0.29491"/>
	<tree name="pipo_19_16.15" bhd="19" h="16.15" crown="6.36" formula="2.351*(min(0.95, hrel)/0.95)^0.29491"/>
	<tree name="pipo_19_18.05" bhd="19" h="18.05" crown="7.11" formula="2.351*(min(0.95, hrel)/0.95)^0.29491"/>
	<tree name="pipo_19_19.95" bhd="19" h="19.95" crown="7.86" formula="2.351*(min(0.95, hrel)/0.95)^0.29491"/>
	<tree name="pipo_20_9" bhd="20" h="9" crown="3.55" formula="2.405*(min(0.95, hrel)/0.95)^0.29491"/>
	<tree name="pipo_20_11" bhd="20" h="11" crown="4.33" formula="2.405*(min(0.95, hrel)/0.95)^0.29491"/>
	<tree name="pipo_20_13" bhd="20" h="13" crown="5.12" formula="2.405*(min(0.95, hrel)/0.95)^0.29491"/>
	<tree name="pipo_20_15" bhd="20" h="15" crown="5.91" formula="2.405*(min(0.95, hrel)/0.95)^0.29491"/>
	<tree name="pipo_20_17" bhd="20" h="17" crown="6.7" formula="2.405*(min(0.95, hrel)/0.95)^0.29491"/>
	<tree name="pipo_20_19" bhd="20" h="19" crown="7.49" formula="2.405*(min(0.95, hrel)/0.95)^0.29491"/>
	<tree name="pipo_20_21" bhd="20" h="21" crown="8.27" formula="2.405*(min(0.95, hrel)/0.95)^0.29491"/>
	<tree name="pipo_21_9.45" bhd="21" h="9.45" crown="3.72" formula="2.459*(min(0.95, hrel)/0.95)^0.29491"/>
	<tree name="pipo_21_11.55" bhd="21" h="11.55" crown="4.55" formula="2.459*(min(0.95, hrel)/0.95)^0.29491"/>
	<tree name="pipo_21_13.65" bhd="21" h="13.65" crown="5.38" formula="2.459*(min(0.95, hrel)/0.95)^0.29491"/>
	<tree name="pipo_21_15.75" bhd="21" h="15.75" crown="6.21" formula="2.459*(min(0.95, hrel)/0.95)^0.29491"/>
	<tree name="pipo_21_17.85" bhd="21" h="17.85" crown="7.03" formula="2.459*(min(0.95, hrel)/0.95)^0.29491"/>
	<tree name="pipo_21_19.95" bhd="21" h="19.95" crown="7.86" formula="2.459*(min(0.95, hrel)/0.95)^0.29491"/>
	<tree name="pipo_21_22.05" bhd="21" h="22.05" crown="8.69" formula="2.459*(min(0.95, hrel)/0.95)^0.29491"/>
	<tree name="pipo_22_9.9" bhd="22" h="9.9" crown="3.9" formula="2.513*(min(0.95, hrel)/0.95)^0.29491"/>
	<tree name="pipo_22_12.1" bhd="22" h="12.1" crown="4.77" formula="2.513*(min(0.95, hrel)/0.95)^0.29491"/>
	<tree name="pipo_22_14.3" bhd="22" h="14.3" crown="5.63" formula="2.513*(min(0.95, hrel)/0.95)^0.29491"/>
	<tree name="pipo_22_16.5" bhd="22" h="16.5" crown="6.5" formula="2.513*(min(0.95, hrel)/0.95)^0.29491"/>
	<tree name="pipo_22_18.7" bhd="22" h="18.7" crown="7.37" formula="2.513*(min(0.95, hrel)/0.95)^0.29491"/>
	<tree name="pipo_22_20.9" bhd="22" h="20.9" crown="8.23" formula="2.513*(min(0.95, hrel)/0.95)^0.29491"/>
	<tree name="pipo_22_23.1" bhd="22" h="23.1" crown="9.1" formula="2.513*(min(0.95, hrel)/0.95)^0.29491"/>
	<tree name="pipo_23_10.35" bhd="23" h="10.35" crown="4.08" formula="2.567*(min(0.95, hrel)/0.95)^0.29491"/>
	<tree name="pipo_23_12.65" bhd="23" h="12.65" crown="4.98" formula="2.567*(min(0.95, hrel)/0.95)^0.29491"/>
	<tree name="pipo_23_14.95" bhd="23" h="14.95" crown="5.89" formula="2.567*(min(0.95, hrel)/0.95)^0.29491"/>
	<tree name="pipo_23_17.25" bhd="23" h="17.25" crown="6.8" formula="2.567*(min(0.95, hrel)/0.95)^0.29491"/>
	<tree name="pipo_23_19.55" bhd="23" h="19.55" crown="7.7" formula="2.567*(min(0.95, hrel)/0.95)^0.29491"/>
	<tree name="pipo_23_21.85" bhd="23" h="21.85" crown="8.61" formula="2.567*(min(0.95, hrel)/0.95)^0.29491"/>
	<tree name="pipo_23_24.15" bhd="23" h="24.15" crown="9.52" formula="2.567*(min(0.95, hrel)/0.95)^0.29491"/>
	<tree name="pipo_24_10.8" bhd="24" h="10.8" crown="4.26" formula="2.62*(min(0.95, hrel)/0.95)^0.29491"/>
	<tree name="pipo_24_13.2" bhd="24" h="13.2" crown="5.2" formula="2.62*(min(0.95, hrel)/0.95)^0.29491"/>
	<tree name="pipo_24_15.6" bhd="24" h="15.6" crown="6.15" formula="2.62*(min(0.95, hrel)/0.95)^0.29491"/>
	<tree name="pipo_24_18" bhd="24" h="18" crown="7.09" formula="2.62*(min(0.95, hrel)/0.95)^0.29491"/>
	<tree name="pipo_24_20.4" bhd="24" h="20.4" crown="8.04" formula="2.62*(min(0.95, hrel)/0.95)^0.29491"/>
	<tree name="pipo_24_22.8" bhd="24" h="22.8" crown="8.98" formula="2.62*(min(0.95, hrel)/0.95)^0.29491"/>
	<tree name="pipo_25_11.25" bhd="25" h="11.25" crown="4.43" formula="2.674*(min(0.95, hrel)/0.95)^0.29491"/>
	<tree name="pipo_25_13.75" bhd="25" h="13.75" crown="5.42" formula="2.674*(min(0.95, hrel)/0.95)^0.29491"/>
	<tree name="pipo_25_16.25" bhd="25" h="16.25" crown="6.4" formula="2.674*(min(0.95, hrel)/0.95)^0.29491"/>
	<tree name="pipo_25_18.75" bhd="25" h="18.75" crown="7.39" formula="2.674*(min(0.95, hrel)/0.95)^0.29491"/>
	<tree name="pipo_25_21.25" bhd="25" h="21.25" crown="8.37" formula="2.674*(min(0.95, hrel)/0.95)^0.29491"/>
	<tree name="pipo_25_23.75" bhd="25" h="23.75" crown="9.36" formula="2.674*(min(0.95, hrel)/0.95)^0.29491"/>
	<tree name="pipo_26_11.7" bhd="26" h="11.7" crown="4.61" formula="2.728*(min(0.95, hrel)/0.95)^0.29491"/>
	<tree name="pipo_26_14.3" bhd="26" h="14.3" crown="5.63" formula="2.728*(min(0.95, hrel)/0.95)^0.29491"/>
	<tree name="pipo_26_16.9" bhd="26" h="16.9" crown="6.66" formula="2.728*(min(0.95, hrel)/0.95)^0.29491"/>
	<tree name="pipo_26_19.5" bhd="26" h="19.5" crown="7.68" formula="2.728*(min(0.95, hrel)/0.95)^0.29491"/>
	<tree name="pipo_26_22.1" bhd="26" h="22.1" crown="8.71" formula="2.728*(min(0.95, hrel)/0.95)^0.29491"/>
	<tree name="pipo_26_24.7" bhd="26" h="24.7" crown="9.73" formula="2.728*(min(0.95, hrel)/0.95)^0.29491"/>
	<tree name="pipo_27_12.15" bhd="27" h="12.15" crown="4.79" formula="2.782*(min(0.95, hrel)/0.95)^0.29491"/>
	<tree name="pipo_27_14.85" bhd="27" h="14.85" crown="5.85" formula="2.782*(min(0.95, hrel)/0.95)^0.29491"/>
	<tree name="pipo_27_17.55" bhd="27" h="17.55" crown="6.91" formula="2.782*(min(0.95, hrel)/0.95)^0.29491"/>
	<tree name="pipo_27_20.25" bhd="27" h="20.25" crown="7.98" formula="2.782*(min(0.95, hrel)/0.95)^0.29491"/>
	<tree name="pipo_27_22.95" bhd="27" h="22.95" crown="9.04" formula="2.782*(min(0.95, hrel)/0.95)^0.29491"/>
	<tree name="pipo_27_25.65" bhd="27" h="25.65" crown="10.11" formula="2.782*(min(0.95, hrel)/0.95)^0.29491"/>
	<tree name="pipo_28_12.6" bhd="28" h="12.6" crown="4.96" formula="2.836*(min(0.95, hrel)/0.95)^0.29491"/>
	<tree name="pipo_28_15.4" bhd="28" h="15.4" crown="6.07" formula="2.836*(min(0.95, hrel)/0.95)^0.29491"/>
	<tree name="pipo_28_18.2" bhd="28" h="18.2" crown="7.17" formula="2.836*(min(0.95, hrel)/0.95)^0.29491"/>
	<tree name="pipo_28_21" bhd="28" h="21" crown="8.27" formula="2.836*(min(0.95, hrel)/0.95)^0.29491"/>
	<tree name="pipo_28_23.8" bhd="28" h="23.8" crown="9.38" formula="2.836*(min(0.95, hrel)/0.95)^0.29491"/>
	<tree name="pipo_28_26.6" bhd="28" h="26.6" crown="10.48" formula="2.836*(min(0.95, hrel)/0.95)^0.29491"/>
	<tree name="pipo_29_13.05" bhd="29" h="13.05" crown="5.14" formula="2.89*(min(0.95, hrel)/0.95)^0.29491"/>
	<tree name="pipo_29_15.95" bhd="29" h="15.95" crown="6.28" formula="2.89*(min(0.95, hrel)/0.95)^0.29491"/>
	<tree name="pipo_29_18.85" bhd="29" h="18.85" crown="7.43" formula="2.89*(min(0.95, hrel)/0.95)^0.29491"/>
	<tree name="pipo_29_21.75" bhd="29" h="21.75" crown="8.57" formula="2.89*(min(0.95, hrel)/0.95)^0.29491"/>
	<tree name="pipo_29_24.65" bhd="29" h="24.65" crown="9.71" formula="2.89*(min(0.95, hrel)/0.95)^0.29491"/>
	<tree name="pipo_29_27.55" bhd="29" h="27.55" crown="10.85" formula="2.89*(min(0.95, hrel)/0.95)^0.29491"/>
	<tree name="pipo_30_13.5" bhd="30" h="13.5" crown="5.32" formula="2.944*(min(0.95, hrel)/0.95)^0.29491"/>
	<tree name="pipo_30_16.5" bhd="30" h="16.5" crown="6.5" formula="2.944*(min(0.95, hrel)/0.95)^0.29491"/>
	<tree name="pipo_30_19.5" bhd="30" h="19.5" crown="7.68" formula="2.944*(min(0.95, hrel)/0.95)^0.29491"/>
	<tree name="pipo_30_22.5" bhd="30" h="22.5" crown="8.87" formula="2.944*(min(0.95, hrel)/0.95)^0.29491"/>
	<tree name="pipo_30_25.5" bhd="30" h="25.5" crown="10.05" formula="2.944*(min(0.95, hrel)/0.95)^0.29491"/>
	<tree name="pipo_30_28.5" bhd="30" h="28.5" crown="11.23" formula="2.944*(min(0.95, hrel)/0.95)^0.29491"/>
	<tree name="pipo_31_13.95" bhd="31" h="13.95" crown="5.5" formula="2.998*(min(0.95, hrel)/0.95)^0.29491"/>
	<tree name="pipo_31_17.05" bhd="31" h="17.05" crown="6.72" formula="2.998*(min(0.95, hrel)/0.95)^0.29491"/>
	<tree name="pipo_31_20.15" bhd="31" h="20.15" crown="7.94" formula="2.998*(min(0.95, hrel)/0.95)^0.29491"/>
	<tree name="pipo_31_23.25" bhd="31" h="23.25" crown="9.16" formula="2.998*(min(0.95, hrel)/0.95)^0.29491"/>
	<tree name="pipo_31_26.35" bhd="31" h="26.35" crown="10.38" formula="2.998*(min(0.95, hrel)/0.95)^0.29491"/>
	<tree name="pipo_31_29.45" bhd="31" h="29.45" crown="11.6" formula="2.998*(min(0.95, hrel)/0.95)^0.29491"/>
	<tree name="pipo_32_14.4" bhd="32" h="14.4" crown="5.67" formula="3.052*(min(0.95, hrel)/0.95)^0.29491"/>
	<tree name="pipo_32_17.6" bhd="32" h="17.6" crown="6.93" formula="3.052*(min(0.95, hrel)/0.95)^0.29491"/>
	<tree name="pipo_32_20.8" bhd="32" h="20.8" crown="8.2" formula="3.052*(min(0.95, hrel)/0.95)^0.29491"/>
	<tree name="pipo_32_24" bhd="32" h="24" crown="9.46" formula="3.052*(min(0.95, hrel)/0.95)^0.29491"/>
	<tree name="pipo_32_27.2" bhd="32" h="27.2" crown="10.72" formula="3.052*(min(0.95, hrel)/0.95)^0.29491"/>
	<tree name="pipo_32_30.4" bhd="32" h="30.4" crown="11.98" formula="3.052*(min(0.95, hrel)/0.95)^0.29491"/>
	<tree name="pipo_33_14.85" bhd="33" h="14.85" crown="5.85" formula="3.106*(min(0.95, hrel)/0.95)^0.29491"/>
	<tree name="pipo_33_18.15" bhd="33" h="18.15" crown="7.15" formula="3.106*(min(0.95, hrel)/0.95)^0.29491"/>
	<tree name="pipo_33_21.45" bhd="33" h="21.45" crown="8.45" formula="3.106*(min(0.95, hrel)/0.95)^0.29491"/>
	<tree name="pipo_33_24.75" bhd="33" h="24.75" crown="9.75" formula="3.106*(min(0.95, hrel)/0.95)^0.29491"/>
	<tree name="pipo_33_28.05" bhd="33" h="28.05" crown="11.05" formula="3.106*(min(0.95, hrel)/0.95)^0.29491"/>
	<tree name="pipo_33_31.35" bhd="33" h="31.35" crown="12.35" formula="3.106*(min(0.95, hrel)/0.95)^0.29491"/>
	<tree name="pipo_34_15.3" bhd="34" h="15.3" crown="6.03" formula="3.16*(min(0.95, hrel)/0.95)^0.29491"/>
	<tree name="pipo_34_18.7" bhd="34" h="18.7" crown="7.37" formula="3.16*(min(0.95, hrel)/0.95)^0.29491"/>
	<tree name="pipo_34_22.1" bhd="34" h="22.1" crown="8.71" formula="3.16*(min(0.95, hrel)/0.95)^0.29491"/>
	<tree name="pipo_34_25.5" bhd="34" h="25.5" crown="10.05" formula="3.16*(min(0.95, hrel)/0.95)^0.29491"/>
	<tree name="pipo_34_28.9" bhd="34" h="28.9" crown="11.39" formula="3.16*(min(0.95, hrel)/0.95)^0.29491"/>
	<tree name="pipo_34_32.3" bhd="34" h="32.3" crown="12.73" formula="3.16*(min(0.95, hrel)/0.95)^0.29491"/>
	<tree name="pipo_35_15.75" bhd="35" h="15.75" crown="6.21" formula="3.213*(min(0.95, hrel)/0.95)^0.29491"/>
	<tree name="pipo_35_19.25" bhd="35" h="19.25" crown="7.58" formula="3.213*(min(0.95, hrel)/0.95)^0.29491"/>
	<tree name="pipo_35_22.75" bhd="35" h="22.75" crown="8.96" formula="3.213*(min(0.95, hrel)/0.95)^0.29491"/>
	<tree name="pipo_35_26.25" bhd="35" h="26.25" crown="10.34" formula="3.213*(min(0.95, hrel)/0.95)^0.29491"/>
	<tree name="pipo_35_29.75" bhd="35" h="29.75" crown="11.72" formula="3.213*(min(0.95, hrel)/0.95)^0.29491"/>
	<tree name="pipo_35_33.25" bhd="35" h="33.25" crown="13.1" formula="3.213*(min(0.95, hrel)/0.95)^0.29491"/>
	<tree name="pipo_36_16.2" bhd="36" h="16.2" crown="6.38" formula="3.267*(min(0.95, hrel)/0.95)^0.29491"/>
	<tree name="pipo_36_19.8" bhd="36" h="19.8" crown="7.8" formula="3.267*(min(0.95, hrel)/0.95)^0.29491"/>
	<tree name="pipo_36_23.4" bhd="36" h="23.4" crown="9.22" formula="3.267*(min(0.95, hrel)/0.95)^0.29491"/>
	<tree name="pipo_36_27" bhd="36" h="27" crown="10.64" formula="3.267*(min(0.95, hrel)/0.95)^0.29491"/>
	<tree name="pipo_36_30.6" bhd="36" h="30.6" crown="12.06" formula="3.267*(min(0.95, hrel)/0.95)^0.29491"/>
	<tree name="pipo_36_34.2" bhd="36" h="34.2" crown="13.47" formula="3.267*(min(0.95, hrel)/0.95)^0.29491"/>
	<tree name="pipo_37_16.65" bhd="37" h="16.65" crown="6.56" formula="3.321*(min(0.95, hrel)/0.95)^0.29491"/>
	<tree name="pipo_37_20.35" bhd="37" h="20.35" crown="8.02" formula="3.321*(min(0.95, hrel)/0.95)^0.29491"/>
	<tree name="pipo_37_24.05" bhd="37" h="24.05" crown="9.48" formula="3.321*(min(0.95, hrel)/0.95)^0.29491"/>
	<tree name="pipo_37_27.75" bhd="37" h="27.75" crown="10.93" formula="3.321*(min(0.95, hrel)/0.95)^0.29491"/>
	<tree name="pipo_37_31.45" bhd="37" h="31.45" crown="12.39" formula="3.321*(min(0.95, hrel)/0.95)^0.29491"/>
	<tree name="pipo_37_35.15" bhd="37" h="35.15" crown="13.85" formula="3.321*(min(0.95, hrel)/0.95)^0.29491"/>
	<tree name="pipo_38_17.1" bhd="38" h="17.1" crown="6.74" formula="3.375*(min(0.95, hrel)/0.95)^0.29491"/>
	<tree name="pipo_38_20.9" bhd="38" h="20.9" crown="8.23" formula="3.375*(min(0.95, hrel)/0.95)^0.29491"/>
	<tree name="pipo_38_24.7" bhd="38" h="24.7" crown="9.73" formula="3.375*(min(0.95, hrel)/0.95)^0.29491"/>
	<tree name="pipo_38_28.5" bhd="38" h="28.5" crown="11.23" formula="3.375*(min(0.95, hrel)/0.95)^0.29491"/>
	<tree name="pipo_38_32.3" bhd="38" h="32.3" crown="12.73" formula="3.375*(min(0.95, hrel)/0.95)^0.29491"/>
	<tree name="pipo_38_36.1" bhd="38" h="36.1" crown="14.22" formula="3.375*(min(0.95, hrel)/0.95)^0.29491"/>
	<tree name="pipo_39_17.55" bhd="39" h="17.55" crown="6.91" formula="3.429*(min(0.95, hrel)/0.95)^0.29491"/>
	<tree name="pipo_39_21.45" bhd="39" h="21.45" crown="8.45" formula="3.429*(min(0.95, hrel)/0.95)^0.29491"/>
	<tree name="pipo_39_25.35" bhd="39" h="25.35" crown="9.99" formula="3.429*(min(0.95, hrel)/0.95)^0.29491"/>
	<tree name="pipo_39_29.25" bhd="39" h="29.25" crown="11.52" formula="3.429*(min(0.95, hrel)/0.95)^0.29491"/>
	<tree name="pipo_39_33.15" bhd="39" h="33.15" crown="13.06" formula="3.429*(min(0.95, hrel)/0.95)^0.29491"/>
	<tree name="pipo_40_18" bhd="40" h="18" crown="7.09" formula="3.483*(min(0.95, hrel)/0.95)^0.29491"/>
	<tree name="pipo_40_22" bhd="40" h="22" crown="8.67" formula="3.483*(min(0.95, hrel)/0.95)^0.29491"/>
	<tree name="pipo_40_26" bhd="40" h="26" crown="10.24" formula="3.483*(min(0.95, hrel)/0.95)^0.29491"/>
	<tree name="pipo_40_30" bhd="40" h="30" crown="11.82" formula="3.483*(min(0.95, hrel)/0.95)^0.29491"/>
	<tree name="pipo_40_34" bhd="40" h="34" crown="13.4" formula="3.483*(min(0.95, hrel)/0.95)^0.29491"/>
	<tree name="pipo_41_18.45" bhd="41" h="18.45" crown="7.27" formula="3.537*(min(0.95, hrel)/0.95)^0.29491"/>
	<tree name="pipo_41_22.55" bhd="41" h="22.55" crown="8.88" formula="3.537*(min(0.95, hrel)/0.95)^0.29491"/>
	<tree name="pipo_41_26.65" bhd="41" h="26.65" crown="10.5" formula="3.537*(min(0.95, hrel)/0.95)^0.29491"/>
	<tree name="pipo_41_30.75" bhd="41" h="30.75" crown="12.12" formula="3.537*(min(0.95, hrel)/0.95)^0.29491"/>
	<tree name="pipo_41_34.85" bhd="41" h="34.85" crown="13.73" formula="3.537*(min(0.95, hrel)/0.95)^0.29491"/>
	<tree name="pipo_42_18.9" bhd="42" h="18.9" crown="7.45" formula="3.591*(min(0.95, hrel)/0.95)^0.29491"/>
	<tree name="pipo_42_23.1" bhd="42" h="23.1" crown="9.1" formula="3.591*(min(0.95, hrel)/0.95)^0.29491"/>
	<tree name="pipo_42_27.3" bhd="42" h="27.3" crown="10.76" formula="3.591*(min(0.95, hrel)/0.95)^0.29491"/>
	<tree name="pipo_42_31.5" bhd="42" h="31.5" crown="12.41" formula="3.591*(min(0.95, hrel)/0.95)^0.29491"/>
	<tree name="pipo_42_35.7" bhd="42" h="35.7" crown="14.07" formula="3.591*(min(0.95, hrel)/0.95)^0.29491"/>
	<tree name="pipo_43_19.35" bhd="43" h="19.35" crown="7.62" formula="3.645*(min(0.95, hrel)/0.95)^0.29491"/>
	<tree name="pipo_43_23.65" bhd="43" h="23.65" crown="9.32" formula="3.645*(min(0.95, hrel)/0.95)^0.29491"/>
	<tree name="pipo_43_27.95" bhd="43" h="27.95" crown="11.01" formula="3.645*(min(0.95, hrel)/0.95)^0.29491"/>
	<tree name="pipo_43_32.25" bhd="43" h="32.25" crown="12.71" formula="3.645*(min(0.95, hrel)/0.95)^0.29491"/>
	<tree name="pipo_43_36.55" bhd="43" h="36.55" crown="14.4" formula="3.645*(min(0.95, hrel)/0.95)^0.29491"/>
	<tree name="pipo_44_19.8" bhd="44" h="19.8" crown="7.8" formula="3.699*(min(0.95, hrel)/0.95)^0.29491"/>
	<tree name="pipo_44_24.2" bhd="44" h="24.2" crown="9.53" formula="3.699*(min(0.95, hrel)/0.95)^0.29491"/>
	<tree name="pipo_44_28.6" bhd="44" h="28.6" crown="11.27" formula="3.699*(min(0.95, hrel)/0.95)^0.29491"/>
	<tree name="pipo_44_33" bhd="44" h="33" crown="13" formula="3.699*(min(0.95, hrel)/0.95)^0.29491"/>
	<tree name="pipo_44_37.4" bhd="44" h="37.4" crown="14.74" formula="3.699*(min(0.95, hrel)/0.95)^0.29491"/>
	<tree name="pipo_45_20.25" bhd="45" h="20.25" crown="7.98" formula="3.753*(min(0.95, hrel)/0.95)^0.29491"/>
	<tree name="pipo_45_24.75" bhd="45" h="24.75" crown="9.75" formula="3.753*(min(0.95, hrel)/0.95)^0.29491"/>
	<tree name="pipo_45_29.25" bhd="45" h="29.25" crown="11.52" formula="3.753*(min(0.95, hrel)/0.95)^0.29491"/>
	<tree name="pipo_45_33.75" bhd="45" h="33.75" crown="13.3" formula="3.753*(min(0.95, hrel)/0.95)^0.29491"/>
	<tree name="pipo_45_38.25" bhd="45" h="38.25" crown="15.07" formula="3.753*(min(0.95, hrel)/0.95)^0.29491"/>
	<tree name="pipo_46_20.7" bhd="46" h="20.7" crown="8.16" formula="3.806*(min(0.95, hrel)/0.95)^0.29491"/>
	<tree name="pipo_46_25.3" bhd="46" h="25.3" crown="9.97" formula="3.806*(min(0.95, hrel)/0.95)^0.29491"/>
	<tree name="pipo_46_29.9" bhd="46" h="29.9" crown="11.78" formula="3.806*(min(0.95, hrel)/0.95)^0.29491"/>
	<tree name="pipo_46_34.5" bhd="46" h="34.5" crown="13.59" formula="3.806*(min(0.95, hrel)/0.95)^0.29491"/>
	<tree name="pipo_46_39.1" bhd="46" h="39.1" crown="15.41" formula="3.806*(min(0.95, hrel)/0.95)^0.29491"/>
	<tree name="pipo_47_21.15" bhd="47" h="21.15" crown="8.33" formula="3.86*(min(0.95, hrel)/0.95)^0.29491"/>
	<tree name="pipo_47_25.85" bhd="47" h="25.85" crown="10.18" formula="3.86*(min(0.95, hrel)/0.95)^0.29491"/>
	<tree name="pipo_47_30.55" bhd="47" h="30.55" crown="12.04" formula="3.86*(min(0.95, hrel)/0.95)^0.29491"/>
	<tree name="pipo_47_35.25" bhd="47" h="35.25" crown="13.89" formula="3.86*(min(0.95, hrel)/0.95)^0.29491"/>
	<tree name="pipo_47_39.95" bhd="47" h="39.95" crown="15.74" formula="3.86*(min(0.95, hrel)/0.95)^0.29491"/>
	<tree name="pipo_48_21.6" bhd="48" h="21.6" crown="8.51" formula="3.914*(min(0.95, hrel)/0.95)^0.29491"/>
	<tree name="pipo_48_26.4" bhd="48" h="26.4" crown="10.4" formula="3.914*(min(0.95, hrel)/0.95)^0.29491"/>
	<tree name="pipo_48_31.2" bhd="48" h="31.2" crown="12.29" formula="3.914*(min(0.95, hrel)/0.95)^0.29491"/>
	<tree name="pipo_48_36" bhd="48" h="36" crown="14.18" formula="3.914*(min(0.95, hrel)/0.95)^0.29491"/>
	<tree name="pipo_48_40.8" bhd="48" h="40.8" crown="16.08" formula="3.914*(min(0.95, hrel)/0.95)^0.29491"/>
	<tree name="pipo_49_22.05" bhd="49" h="22.05" crown="8.69" formula="3.968*(min(0.95, hrel)/0.95)^0.29491"/>
	<tree name="pipo_49_26.95" bhd="49" h="26.95" crown="10.62" formula="3.968*(min(0.95, hrel)/0.95)^0.29491"/>
	<tree name="pipo_49_31.85" bhd="49" h="31.85" crown="12.55" formula="3.968*(min(0.95, hrel)/0.95)^0.29491"/>
	<tree name="pipo_49_36.75" bhd="49" h="36.75" crown="14.48" formula="3.968*(min(0.95, hrel)/0.95)^0.29491"/>
	<tree name="pipo_49_41.65" bhd="49" h="41.65" crown="16.41" formula="3.968*(min(0.95, hrel)/0.95)^0.29491"/>
	<tree name="pipo_50_22.5" bhd="50" h="22.5" crown="8.87" formula="4.022*(min(0.95, hrel)/0.95)^0.29491"/>
	<tree name="pipo_50_27.5" bhd="50" h="27.5" crown="10.84" formula="4.022*(min(0.95, hrel)/0.95)^0.29491"/>
	<tree name="pipo_50_32.5" bhd="50" h="32.5" crown="12.8" formula="4.022*(min(0.95, hrel)/0.95)^0.29491"/>
	<tree name="pipo_50_37.5" bhd="50" h="37.5" crown="14.78" formula="4.022*(min(0.95, hrel)/0.95)^0.29491"/>
	<tree name="pipo_50_42.5" bhd="50" h="42.5" crown="16.75" formula="4.022*(min(0.95, hrel)/0.95)^0.29491"/>
	<tree name="pipo_51_22.95" bhd="51" h="22.95" crown="9.04" formula="4.076*(min(0.95, hrel)/0.95)^0.29491"/>
	<tree name="pipo_51_28.05" bhd="51" h="28.05" crown="11.05" formula="4.076*(min(0.95, hrel)/0.95)^0.29491"/>
	<tree name="pipo_51_33.15" bhd="51" h="33.15" crown="13.06" formula="4.076*(min(0.95, hrel)/0.95)^0.29491"/>
	<tree name="pipo_51_38.25" bhd="51" h="38.25" crown="15.07" formula="4.076*(min(0.95, hrel)/0.95)^0.29491"/>
	<tree name="pipo_51_43.35" bhd="51" h="43.35" crown="17.08" formula="4.076*(min(0.95, hrel)/0.95)^0.29491"/>
	<tree name="pipo_52_23.4" bhd="52" h="23.4" crown="9.22" formula="4.13*(min(0.95, hrel)/0.95)^0.29491"/>
	<tree name="pipo_52_28.6" bhd="52" h="28.6" crown="11.27" formula="4.13*(min(0.95, hrel)/0.95)^0.29491"/>
	<tree name="pipo_52_33.8" bhd="52" h="33.8" crown="13.32" formula="4.13*(min(0.95, hrel)/0.95)^0.29491"/>
	<tree name="pipo_52_39" bhd="52" h="39" crown="15.37" formula="4.13*(min(0.95, hrel)/0.95)^0.29491"/>
	<tree name="pipo_52_44.2" bhd="52" h="44.2" crown="17.41" formula="4.13*(min(0.95, hrel)/0.95)^0.29491"/>
	<tree name="pipo_53_23.85" bhd="53" h="23.85" crown="9.4" formula="4.184*(min(0.95, hrel)/0.95)^0.29491"/>
	<tree name="pipo_53_29.15" bhd="53" h="29.15" crown="11.49" formula="4.184*(min(0.95, hrel)/0.95)^0.29491"/>
	<tree name="pipo_53_34.45" bhd="53" h="34.45" crown="13.57" formula="4.184*(min(0.95, hrel)/0.95)^0.29491"/>
	<tree name="pipo_53_39.75" bhd="53" h="39.75" crown="15.66" formula="4.184*(min(0.95, hrel)/0.95)^0.29491"/>
	<tree name="pipo_53_45.05" bhd="53" h="45.05" crown="17.75" formula="4.184*(min(0.95, hrel)/0.95)^0.29491"/>
	<tree name="pipo_54_24.3" bhd="54" h="24.3" crown="9.57" formula="4.238*(min(0.95, hrel)/0.95)^0.29491"/>
	<tree name="pipo_54_29.7" bhd="54" h="29.7" crown="11.7" formula="4.238*(min(0.95, hrel)/0.95)^0.29491"/>
	<tree name="pipo_54_35.1" bhd="54" h="35.1" crown="13.83" formula="4.238*(min(0.95, hrel)/0.95)^0.29491"/>
	<tree name="pipo_54_40.5" bhd="54" h="40.5" crown="15.96" formula="4.238*(min(0.95, hrel)/0.95)^0.29491"/>
	<tree name="pipo_54_45.9" bhd="54" h="45.9" crown="18.08" formula="4.238*(min(0.95, hrel)/0.95)^0.29491"/>
	<tree name="pipo_55_24.75" bhd="55" h="24.75" crown="9.75" formula="4.292*(min(0.95, hrel)/0.95)^0.29491"/>
	<tree name="pipo_55_30.25" bhd="55" h="30.25" crown="11.92" formula="4.292*(min(0.95, hrel)/0.95)^0.29491"/>
	<tree name="pipo_55_35.75" bhd="55" h="35.75" crown="14.09" formula="4.292*(min(0.95, hrel)/0.95)^0.29491"/>
	<tree name="pipo_55_41.25" bhd="55" h="41.25" crown="16.25" formula="4.292*(min(0.95, hrel)/0.95)^0.29491"/>
	<tree name="pipo_55_46.75" bhd="55" h="46.75" crown="18.42" formula="4.292*(min(0.95, hrel)/0.95)^0.29491"/>
	<tree name="pipo_56_25.2" bhd="56" h="25.2" crown="9.93" formula="4.346*(min(0.95, hrel)/0.95)^0.29491"/>
	<tree name="pipo_56_30.8" bhd="56" h="30.8" crown="12.14" formula="4.346*(min(0.95, hrel)/0.95)^0.29491"/>
	<tree name="pipo_56_36.4" bhd="56" h="36.4" crown="14.34" formula="4.346*(min(0.95, hrel)/0.95)^0.29491"/>
	<tree name="pipo_56_42" bhd="56" h="42" crown="16.55" formula="4.346*(min(0.95, hrel)/0.95)^0.29491"/>
	<tree name="pipo_56_47.6" bhd="56" h="47.6" crown="18.75" formula="4.346*(min(0.95, hrel)/0.95)^0.29491"/>
	<tree name="pipo_57_25.65" bhd="57" h="25.65" crown="10.11" formula="4.399*(min(0.95, hrel)/0.95)^0.29491"/>
	<tree name="pipo_57_31.35" bhd="57" h="31.35" crown="12.35" formula="4.399*(min(0.95, hrel)/0.95)^0.29491"/>
	<tree name="pipo_57_37.05" bhd="57" h="37.05" crown="14.6" formula="4.399*(min(0.95, hrel)/0.95)^0.29491"/>
	<tree name="pipo_57_42.75" bhd="57" h="42.75" crown="16.84" formula="4.399*(min(0.95, hrel)/0.95)^0.29491"/>
	<tree name="pipo_57_48.45" bhd="57" h="48.45" crown="19.09" formula="4.399*(min(0.95, hrel)/0.95)^0.29491"/>
	<tree name="pipo_58_26.1" bhd="58" h="26.1" crown="10.28" formula="4.453*(min(0.95, hrel)/0.95)^0.29491"/>
	<tree name="pipo_58_31.9" bhd="58" h="31.9" crown="12.57" formula="4.453*(min(0.95, hrel)/0.95)^0.29491"/>
	<tree name="pipo_58_37.7" bhd="58" h="37.7" crown="14.85" formula="4.453*(min(0.95, hrel)/0.95)^0.29491"/>
	<tree name="pipo_58_43.5" bhd="58" h="43.5" crown="17.14" formula="4.453*(min(0.95, hrel)/0.95)^0.29491"/>
	<tree name="pipo_58_49.3" bhd="58" h="49.3" crown="19.42" formula="4.453*(min(0.95, hrel)/0.95)^0.29491"/>
	<tree name="pipo_59_26.55" bhd="59" h="26.55" crown="10.46" formula="4.507*(min(0.95, hrel)/0.95)^0.29491"/>
	<tree name="pipo_59_32.45" bhd="59" h="32.45" crown="12.79" formula="4.507*(min(0.95, hrel)/0.95)^0.29491"/>
	<tree name="pipo_59_38.35" bhd="59" h="38.35" crown="15.11" formula="4.507*(min(0.95, hrel)/0.95)^0.29491"/>
	<tree name="pipo_59_44.25" bhd="59" h="44.25" crown="17.43" formula="4.507*(min(0.95, hrel)/0.95)^0.29491"/>
	<tree name="pipo_59_50.15" bhd="59" h="50.15" crown="19.76" formula="4.507*(min(0.95, hrel)/0.95)^0.29491"/>
	<tree name="pipo_60_27" bhd="60" h="27" crown="10.64" formula="4.561*(min(0.95, hrel)/0.95)^0.29491"/>
	<tree name="pipo_60_33" bhd="60" h="33" crown="13" formula="4.561*(min(0.95, hrel)/0.95)^0.29491"/>
	<tree name="pipo_60_39" bhd="60" h="39" crown="15.37" formula="4.561*(min(0.95, hrel)/0.95)^0.29491"/>
	<tree name="pipo_60_45" bhd="60" h="45" crown="17.73" formula="4.561*(min(0.95, hrel)/0.95)^0.29491"/>
	<tree name="pipo_60_51" bhd="60" h="51" crown="20.09" formula="4.561*(min(0.95, hrel)/0.95)^0.29491"/>
	<tree name="pipo_61_27.45" bhd="61" h="27.45" crown="10.82" formula="4.615*(min(0.95, hrel)/0.95)^0.29491"/>
	<tree name="pipo_61_33.55" bhd="61" h="33.55" crown="13.22" formula="4.615*(min(0.95, hrel)/0.95)^0.29491"/>
	<tree name="pipo_61_39.65" bhd="61" h="39.65" crown="15.62" formula="4.615*(min(0.95, hrel)/0.95)^0.29491"/>
	<tree name="pipo_61_45.75" bhd="61" h="45.75" crown="18.03" formula="4.615*(min(0.95, hrel)/0.95)^0.29491"/>
	<tree name="pipo_61_51.85" bhd="61" h="51.85" crown="20.43" formula="4.615*(min(0.95, hrel)/0.95)^0.29491"/>
	<tree name="pipo_62_27.9" bhd="62" h="27.9" crown="10.99" formula="4.669*(min(0.95, hrel)/0.95)^0.29491"/>
	<tree name="pipo_62_34.1" bhd="62" h="34.1" crown="13.44" formula="4.669*(min(0.95, hrel)/0.95)^0.29491"/>
	<tree name="pipo_62_40.3" bhd="62" h="40.3" crown="15.88" formula="4.669*(min(0.95, hrel)/0.95)^0.29491"/>
	<tree name="pipo_62_46.5" bhd="62" h="46.5" crown="18.32" formula="4.669*(min(0.95, hrel)/0.95)^0.29491"/>
	<tree name="pipo_62_52.7" bhd="62" h="52.7" crown="20.76" formula="4.669*(min(0.95, hrel)/0.95)^0.29491"/>
	<tree name="pipo_63_28.35" bhd="63" h="28.35" crown="11.17" formula="4.723*(min(0.95, hrel)/0.95)^0.29491"/>
	<tree name="pipo_63_34.65" bhd="63" h="34.65" crown="13.65" formula="4.723*(min(0.95, hrel)/0.95)^0.29491"/>
	<tree name="pipo_63_40.95" bhd="63" h="40.95" crown="16.13" formula="4.723*(min(0.95, hrel)/0.95)^0.29491"/>
	<tree name="pipo_63_47.25" bhd="63" h="47.25" crown="18.62" formula="4.723*(min(0.95, hrel)/0.95)^0.29491"/>
	<tree name="pipo_63_53.55" bhd="63" h="53.55" crown="21.1" formula="4.723*(min(0.95, hrel)/0.95)^0.29491"/>
	<tree name="pipo_64_28.8" bhd="64" h="28.8" crown="11.35" formula="4.777*(min(0.95, hrel)/0.95)^0.29491"/>
	<tree name="pipo_64_35.2" bhd="64" h="35.2" crown="13.87" formula="4.777*(min(0.95, hrel)/0.95)^0.29491"/>
	<tree name="pipo_64_41.6" bhd="64" h="41.6" crown="16.39" formula="4.777*(min(0.95, hrel)/0.95)^0.29491"/>
	<tree name="pipo_64_48" bhd="64" h="48" crown="18.91" formula="4.777*(min(0.95, hrel)/0.95)^0.29491"/>
	<tree name="pipo_64_54.4" bhd="64" h="54.4" crown="21.43" formula="4.777*(min(0.95, hrel)/0.95)^0.29491"/>
	<tree name="pipo_65_29.25" bhd="65" h="29.25" crown="11.52" formula="4.831*(min(0.95, hrel)/0.95)^0.29491"/>
	<tree name="pipo_65_35.75" bhd="65" h="35.75" crown="14.09" formula="4.831*(min(0.95, hrel)/0.95)^0.29491"/>
	<tree name="pipo_65_42.25" bhd="65" h="42.25" crown="16.65" formula="4.831*(min(0.95, hrel)/0.95)^0.29491"/>
	<tree name="pipo_65_48.75" bhd="65" h="48.75" crown="19.21" formula="4.831*(min(0.95, hrel)/0.95)^0.29491"/>
	<tree name="pipo_65_55.25" bhd="65" h="55.25" crown="21.77" formula="4.831*(min(0.95, hrel)/0.95)^0.29491"/>
	<tree name="pipo_66_29.7" bhd="66" h="29.7" crown="11.7" formula="4.885*(min(0.95, hrel)/0.95)^0.29491"/>
	<tree name="pipo_66_36.3" bhd="66" h="36.3" crown="14.3" formula="4.885*(min(0.95, hrel)/0.95)^0.29491"/>
	<tree name="pipo_66_42.9" bhd="66" h="42.9" crown="16.9" formula="4.885*(min(0.95, hrel)/0.95)^0.29491"/>
	<tree name="pipo_66_49.5" bhd="66" h="49.5" crown="19.5" formula="4.885*(min(0.95, hrel)/0.95)^0.29491"/>
	<tree name="pipo_66_56.1" bhd="66" h="56.1" crown="22.1" formula="4.885*(min(0.95, hrel)/0.95)^0.29491"/>
	<tree name="pipo_67_30.15" bhd="67" h="30.15" crown="11.88" formula="4.939*(min(0.95, hrel)/0.95)^0.29491"/>
	<tree name="pipo_67_36.85" bhd="67" h="36.85" crown="14.52" formula="4.939*(min(0.95, hrel)/0.95)^0.29491"/>
	<tree name="pipo_67_43.55" bhd="67" h="43.55" crown="17.16" formula="4.939*(min(0.95, hrel)/0.95)^0.29491"/>
	<tree name="pipo_67_50.25" bhd="67" h="50.25" crown="19.8" formula="4.939*(min(0.95, hrel)/0.95)^0.29491"/>
	<tree name="pipo_67_56.95" bhd="67" h="56.95" crown="22.44" formula="4.939*(min(0.95, hrel)/0.95)^0.29491"/>
	<tree name="pipo_68_30.6" bhd="68" h="30.6" crown="12.06" formula="4.992*(min(0.95, hrel)/0.95)^0.29491"/>
	<tree name="pipo_68_37.4" bhd="68" h="37.4" crown="14.74" formula="4.992*(min(0.95, hrel)/0.95)^0.29491"/>
	<tree name="pipo_68_44.2" bhd="68" h="44.2" crown="17.41" formula="4.992*(min(0.95, hrel)/0.95)^0.29491"/>
	<tree name="pipo_68_51" bhd="68" h="51" crown="20.09" formula="4.992*(min(0.95, hrel)/0.95)^0.29491"/>
	<tree name="pipo_69_31.05" bhd="69" h="31.05" crown="12.23" formula="5.046*(min(0.95, hrel)/0.95)^0.29491"/>
	<tree name="pipo_69_37.95" bhd="69" h="37.95" crown="14.95" formula="5.046*(min(0.95, hrel)/0.95)^0.29491"/>
	<tree name="pipo_69_44.85" bhd="69" h="44.85" crown="17.67" formula="5.046*(min(0.95, hrel)/0.95)^0.29491"/>
	<tree name="pipo_69_51.75" bhd="69" h="51.75" crown="20.39" formula="5.046*(min(0.95, hrel)/0.95)^0.29491"/>
	<tree name="pipo_70_31.5" bhd="70" h="31.5" crown="12.41" formula="5.1*(min(0.95, hrel)/0.95)^0.29491"/>
	<tree name="pipo_70_38.5" bhd="70" h="38.5" crown="15.17" formula="5.1*(min(0.95, hrel)/0.95)^0.29491"/>
	<tree name="pipo_70_45.5" bhd="70" h="45.5" crown="17.93" formula="5.1*(min(0.95, hrel)/0.95)^0.29491"/>
	<tree name="pipo_70_52.5" bhd="70" h="52.5" crown="20.69" formula="5.1*(min(0.95, hrel)/0.95)^0.29491"/>
	<tree name="pipo_71_31.95" bhd="71" h="31.95" crown="12.59" formula="5.154*(min(0.95, hrel)/0.95)^0.29491"/>
	<tree name="pipo_71_39.05" bhd="71" h="39.05" crown="15.39" formula="5.154*(min(0.95, hrel)/0.95)^0.29491"/>
	<tree name="pipo_71_46.15" bhd="71" h="46.15" crown="18.18" formula="5.154*(min(0.95, hrel)/0.95)^0.29491"/>
	<tree name="pipo_71_53.25" bhd="71" h="53.25" crown="20.98" formula="5.154*(min(0.95, hrel)/0.95)^0.29491"/>
	<tree name="pipo_72_32.4" bhd="72" h="32.4" crown="12.77" formula="5.208*(min(0.95, hrel)/0.95)^0.29491"/>
	<tree name="pipo_72_39.6" bhd="72" h="39.6" crown="15.6" formula="5.208*(min(0.95, hrel)/0.95)^0.29491"/>
	<tree name="pipo_72_46.8" bhd="72" h="46.8" crown="18.44" formula="5.208*(min(0.95, hrel)/0.95)^0.29491"/>
	<tree name="pipo_72_54" bhd="72" h="54" crown="21.28" formula="5.208*(min(0.95, hrel)/0.95)^0.29491"/>
	<tree name="pipo_73_32.85" bhd="73" h="32.85" crown="12.94" formula="5.262*(min(0.95, hrel)/0.95)^0.29491"/>
	<tree name="pipo_73_40.15" bhd="73" h="40.15" crown="15.82" formula="5.262*(min(0.95, hrel)/0.95)^0.29491"/>
	<tree name="pipo_73_47.45" bhd="73" h="47.45" crown="18.7" formula="5.262*(min(0.95, hrel)/0.95)^0.29491"/>
	<tree name="pipo_73_54.75" bhd="73" h="54.75" crown="21.57" formula="5.262*(min(0.95, hrel)/0.95)^0.29491"/>
	<tree name="pipo_74_33.3" bhd="74" h="33.3" crown="13.12" formula="5.316*(min(0.95, hrel)/0.95)^0.29491"/>
	<tree name="pipo_74_40.7" bhd="74" h="40.7" crown="16.04" formula="5.316*(min(0.95, hrel)/0.95)^0.29491"/>
	<tree name="pipo_74_48.1" bhd="74" h="48.1" crown="18.95" formula="5.316*(min(0.95, hrel)/0.95)^0.29491"/>
	<tree name="pipo_74_55.5" bhd="74" h="55.5" crown="21.87" formula="5.316*(min(0.95, hrel)/0.95)^0.29491"/>
	<tree name="pipo_75_33.75" bhd="75" h="33.75" crown="13.3" formula="5.37*(min(0.95, hrel)/0.95)^0.29491"/>
	<tree name="pipo_75_41.25" bhd="75" h="41.25" crown="16.25" formula="5.37*(min(0.95, hrel)/0.95)^0.29491"/>
	<tree name="pipo_75_48.75" bhd="75" h="48.75" crown="19.21" formula="5.37*(min(0.95, hrel)/0.95)^0.29491"/>
	<tree name="pipo_75_56.25" bhd="75" h="56.25" crown="22.16" formula="5.37*(min(0.95, hrel)/0.95)^0.29491"/>
	<tree name="pipo_76_34.2" bhd="76" h="34.2" crown="13.47" formula="5.424*(min(0.95, hrel)/0.95)^0.29491"/>
	<tree name="pipo_76_41.8" bhd="76" h="41.8" crown="16.47" formula="5.424*(min(0.95, hrel)/0.95)^0.29491"/>
	<tree name="pipo_76_49.4" bhd="76" h="49.4" crown="19.46" formula="5.424*(min(0.95, hrel)/0.95)^0.29491"/>
	<tree name="pipo_76_57" bhd="76" h="57" crown="22.46" formula="5.424*(min(0.95, hrel)/0.95)^0.29491"/>
	<tree name="pipo_77_34.65" bhd="77" h="34.65" crown="13.65" formula="5.478*(min(0.95, hrel)/0.95)^0.29491"/>
	<tree name="pipo_77_42.35" bhd="77" h="42.35" crown="16.69" formula="5.478*(min(0.95, hrel)/0.95)^0.29491"/>
	<tree name="pipo_77_50.05" bhd="77" h="50.05" crown="19.72" formula="5.478*(min(0.95, hrel)/0.95)^0.29491"/>
	<tree name="pipo_77_57.75" bhd="77" h="57.75" crown="22.75" formula="5.478*(min(0.95, hrel)/0.95)^0.29491"/>
	<tree name="pipo_78_35.1" bhd="78" h="35.1" crown="13.83" formula="5.532*(min(0.95, hrel)/0.95)^0.29491"/>
	<tree name="pipo_78_42.9" bhd="78" h="42.9" crown="16.9" formula="5.532*(min(0.95, hrel)/0.95)^0.29491"/>
	<tree name="pipo_78_50.7" bhd="78" h="50.7" crown="19.98" formula="5.532*(min(0.95, hrel)/0.95)^0.29491"/>
	<tree name="pipo_78_58.5" bhd="78" h="58.5" crown="23.05" formula="5.532*(min(0.95, hrel)/0.95)^0.29491"/>
	<tree name="pipo_79_35.55" bhd="79" h="35.55" crown="14.01" formula="5.585*(min(0.95, hrel)/0.95)^0.29491"/>
	<tree name="pipo_79_43.45" bhd="79" h="43.45" crown="17.12" formula="5.585*(min(0.95, hrel)/0.95)^0.29491"/>
	<tree name="pipo_79_51.35" bhd="79" h="51.35" crown="20.23" formula="5.585*(min(0.95, hrel)/0.95)^0.29491"/>
	<tree name="pipo_79_59.25" bhd="79" h="59.25" crown="23.34" formula="5.585*(min(0.95, hrel)/0.95)^0.29491"/>
	<tree name="pipo_80_36" bhd="80" h="36" crown="14.18" formula="5.639*(min(0.95, hrel)/0.95)^0.29491"/>
	<tree name="pipo_80_44" bhd="80" h="44" crown="17.34" formula="5.639*(min(0.95, hrel)/0.95)^0.29491"/>
	<tree name="pipo_80_52" bhd="80" h="52" crown="20.49" formula="5.639*(min(0.95, hrel)/0.95)^0.29491"/>
	<tree name="pipo_80_60" bhd="80" h="60" crown="23.64" formula="5.639*(min(0.95, hrel)/0.95)^0.29491"/>
	<tree name="pipo_81_36.45" bhd="81" h="36.45" crown="14.36" formula="5.693*(min(0.95, hrel)/0.95)^0.29491"/>
	<tree name="pipo_81_44.55" bhd="81" h="44.55" crown="17.55" formula="5.693*(min(0.95, hrel)/0.95)^0.29491"/>
	<tree name="pipo_81_52.65" bhd="81" h="52.65" crown="20.74" formula="5.693*(min(0.95, hrel)/0.95)^0.29491"/>
	<tree name="pipo_81_60.75" bhd="81" h="60.75" crown="23.94" formula="5.693*(min(0.95, hrel)/0.95)^0.29491"/>
	<tree name="pipo_82_36.9" bhd="82" h="36.9" crown="14.54" formula="5.747*(min(0.95, hrel)/0.95)^0.29491"/>
	<tree name="pipo_82_45.1" bhd="82" h="45.1" crown="17.77" formula="5.747*(min(0.95, hrel)/0.95)^0.29491"/>
	<tree name="pipo_82_53.3" bhd="82" h="53.3" crown="21" formula="5.747*(min(0.95, hrel)/0.95)^0.29491"/>
	<tree name="pipo_82_61.5" bhd="82" h="61.5" crown="24.23" formula="5.747*(min(0.95, hrel)/0.95)^0.29491"/>
	<tree name="pipo_83_37.35" bhd="83" h="37.35" crown="14.72" formula="5.801*(min(0.95, hrel)/0.95)^0.29491"/>
	<tree name="pipo_83_45.65" bhd="83" h="45.65" crown="17.99" formula="5.801*(min(0.95, hrel)/0.95)^0.29491"/>
	<tree name="pipo_83_53.95" bhd="83" h="53.95" crown="21.26" formula="5.801*(min(0.95, hrel)/0.95)^0.29491"/>
	<tree name="pipo_83_62.25" bhd="83" h="62.25" crown="24.53" formula="5.801*(min(0.95, hrel)/0.95)^0.29491"/>
	<tree name="pipo_84_37.8" bhd="84" h="37.8" crown="14.89" formula="5.855*(min(0.95, hrel)/0.95)^0.29491"/>
	<tree name="pipo_84_46.2" bhd="84" h="46.2" crown="18.2" formula="5.855*(min(0.95, hrel)/0.95)^0.29491"/>
	<tree name="pipo_84_54.6" bhd="84" h="54.6" crown="21.51" formula="5.855*(min(0.95, hrel)/0.95)^0.29491"/>
	<tree name="pipo_84_63" bhd="84" h="63" crown="24.82" formula="5.855*(min(0.95, hrel)/0.95)^0.29491"/>
	<tree name="pipo_85_38.25" bhd="85" h="38.25" crown="15.07" formula="5.909*(min(0.95, hrel)/0.95)^0.29491"/>
	<tree name="pipo_85_46.75" bhd="85" h="46.75" crown="18.42" formula="5.909*(min(0.95, hrel)/0.95)^0.29491"/>
	<tree name="pipo_85_55.25" bhd="85" h="55.25" crown="21.77" formula="5.909*(min(0.95, hrel)/0.95)^0.29491"/>
	<tree name="pipo_85_63.75" bhd="85" h="63.75" crown="25.12" formula="5.909*(min(0.95, hrel)/0.95)^0.29491"/>
	<tree name="pipo_86_38.7" bhd="86" h="38.7" crown="15.25" formula="5.963*(min(0.95, hrel)/0.95)^0.29491"/>
	<tree name="pipo_86_47.3" bhd="86" h="47.3" crown="18.64" formula="5.963*(min(0.95, hrel)/0.95)^0.29491"/>
	<tree name="pipo_86_55.9" bhd="86" h="55.9" crown="22.02" formula="5.963*(min(0.95, hrel)/0.95)^0.29491"/>
	<tree name="pipo_86_64.5" bhd="86" h="64.5" crown="25.41" formula="5.963*(min(0.95, hrel)/0.95)^0.29491"/>
	<tree name="pipo_87_39.15" bhd="87" h="39.15" crown="15.43" formula="6.017*(min(0.95, hrel)/0.95)^0.29491"/>
	<tree name="pipo_87_47.85" bhd="87" h="47.85" crown="18.85" formula="6.017*(min(0.95, hrel)/0.95)^0.29491"/>
	<tree name="pipo_87_56.55" bhd="87" h="56.55" crown="22.28" formula="6.017*(min(0.95, hrel)/0.95)^0.29491"/>
	<tree name="pipo_87_65.25" bhd="87" h="65.25" crown="25.71" formula="6.017*(min(0.95, hrel)/0.95)^0.29491"/>
	<tree name="pipo_88_39.6" bhd="88" h="39.6" crown="15.6" formula="6.071*(min(0.95, hrel)/0.95)^0.29491"/>
	<tree name="pipo_88_48.4" bhd="88" h="48.4" crown="19.07" formula="6.071*(min(0.95, hrel)/0.95)^0.29491"/>
	<tree name="pipo_88_57.2" bhd="88" h="57.2" crown="22.54" formula="6.071*(min(0.95, hrel)/0.95)^0.29491"/>
	<tree name="pipo_88_66" bhd="88" h="66" crown="26" formula="6.071*(min(0.95, hrel)/0.95)^0.29491"/>
	<tree name="pipo_89_40.05" bhd="89" h="40.05" crown="15.78" formula="6.125*(min(0.95, hrel)/0.95)^0.29491"/>
	<tree name="pipo_89_48.95" bhd="89" h="48.95" crown="19.29" formula="6.125*(min(0.95, hrel)/0.95)^0.29491"/>
	<tree name="pipo_89_57.85" bhd="89" h="57.85" crown="22.79" formula="6.125*(min(0.95, hrel)/0.95)^0.29491"/>
	<tree name="pipo_89_66.75" bhd="89" h="66.75" crown="26.3" formula="6.125*(min(0.95, hrel)/0.95)^0.29491"/>
	<tree name="pipo_90_40.5" bhd="90" h="40.5" crown="15.96" formula="6.178*(min(0.95, hrel)/0.95)^0.29491"/>
	<tree name="pipo_90_49.5" bhd="90" h="49.5" crown="19.5" formula="6.178*(min(0.95, hrel)/0.95)^0.29491"/>
	<tree name="pipo_90_58.5" bhd="90" h="58.5" crown="23.05" formula="6.178*(min(0.95, hrel)/0.95)^0.29491"/>
	<tree name="pipo_90_67.5" bhd="90" h="67.5" crown="26.6" formula="6.178*(min(0.95, hrel)/0.95)^0.29491"/>
	<tree name="pipo_91_40.95" bhd="91" h="40.95" crown="16.13" formula="6.232*(min(0.95, hrel)/0.95)^0.29491"/>
	<tree name="pipo_91_50.05" bhd="91" h="50.05" crown="19.72" formula="6.232*(min(0.95, hrel)/0.95)^0.29491"/>
	<tree name="pipo_91_59.15" bhd="91" h="59.15" crown="23.31" formula="6.232*(min(0.95, hrel)/0.95)^0.29491"/>
	<tree name="pipo_91_68.25" bhd="91" h="68.25" crown="26.89" formula="6.232*(min(0.95, hrel)/0.95)^0.29491"/>
	<tree name="pipo_92_41.4" bhd="92" h="41.4" crown="16.31" formula="6.286*(min(0.95, hrel)/0.95)^0.29491"/>
	<tree name="pipo_92_50.6" bhd="92" h="50.6" crown="19.94" formula="6.286*(min(0.95, hrel)/0.95)^0.29491"/>
	<tree name="pipo_92_59.8" bhd="92" h="59.8" crown="23.56" formula="6.286*(min(0.95, hrel)/0.95)^0.29491"/>
	<tree name="pipo_92_69" bhd="92" h="69" crown="27.19" formula="6.286*(min(0.95, hrel)/0.95)^0.29491"/>
	<tree name="pipo_93_41.85" bhd="93" h="41.85" crown="16.49" formula="6.34*(min(0.95, hrel)/0.95)^0.29491"/>
	<tree name="pipo_93_51.15" bhd="93" h="51.15" crown="20.15" formula="6.34*(min(0.95, hrel)/0.95)^0.29491"/>
	<tree name="pipo_93_60.45" bhd="93" h="60.45" crown="23.82" formula="6.34*(min(0.95, hrel)/0.95)^0.29491"/>
	<tree name="pipo_93_69.75" bhd="93" h="69.75" crown="27.48" formula="6.34*(min(0.95, hrel)/0.95)^0.29491"/>
	<tree name="pipo_94_42.3" bhd="94" h="42.3" crown="16.67" formula="6.394*(min(0.95, hrel)/0.95)^0.29491"/>
	<tree name="pipo_94_51.7" bhd="94" h="51.7" crown="20.37" formula="6.394*(min(0.95, hrel)/0.95)^0.29491"/>
	<tree name="pipo_94_61.1" bhd="94" h="61.1" crown="24.07" formula="6.394*(min(0.95, hrel)/0.95)^0.29491"/>
	<tree name="pipo_94_70.5" bhd="94" h="70.5" crown="27.78" formula="6.394*(min(0.95, hrel)/0.95)^0.29491"/>
	<tree name="pipo_95_42.75" bhd="95" h="42.75" crown="16.84" formula="6.448*(min(0.95, hrel)/0.95)^0.29491"/>
	<tree name="pipo_95_52.25" bhd="95" h="52.25" crown="20.59" formula="6.448*(min(0.95, hrel)/0.95)^0.29491"/>
	<tree name="pipo_95_61.75" bhd="95" h="61.75" crown="24.33" formula="6.448*(min(0.95, hrel)/0.95)^0.29491"/>
	<tree name="pipo_95_71.25" bhd="95" h="71.25" crown="28.07" formula="6.448*(min(0.95, hrel)/0.95)^0.29491"/>
	<tree name="pipo_96_43.2" bhd="96" h="43.2" crown="17.02" formula="6.502*(min(0.95, hrel)/0.95)^0.29491"/>
	<tree name="pipo_96_52.8" bhd="96" h="52.8" crown="20.8" formula="6.502*(min(0.95, hrel)/0.95)^0.29491"/>
	<tree name="pipo_96_62.4" bhd="96" h="62.4" crown="24.59" formula="6.502*(min(0.95, hrel)/0.95)^0.29491"/>
	<tree name="pipo_96_72" bhd="96" h="72" crown="28.37" formula="6.502*(min(0.95, hrel)/0.95)^0.29491"/>
	<tree name="pipo_97_43.65" bhd="97" h="43.65" crown="17.2" formula="6.556*(min(0.95, hrel)/0.95)^0.29491"/>
	<tree name="pipo_97_53.35" bhd="97" h="53.35" crown="21.02" formula="6.556*(min(0.95, hrel)/0.95)^0.29491"/>
	<tree name="pipo_97_63.05" bhd="97" h="63.05" crown="24.84" formula="6.556*(min(0.95, hrel)/0.95)^0.29491"/>
	<tree name="pipo_97_72.75" bhd="97" h="72.75" crown="28.66" formula="6.556*(min(0.95, hrel)/0.95)^0.29491"/>
	<tree name="pipo_98_44.1" bhd="98" h="44.1" crown="17.38" formula="6.61*(min(0.95, hrel)/0.95)^0.29491"/>
	<tree name="pipo_98_53.9" bhd="98" h="53.9" crown="21.24" formula="6.61*(min(0.95, hrel)/0.95)^0.29491"/>
	<tree name="pipo_98_63.7" bhd="98" h="63.7" crown="25.1" formula="6.61*(min(0.95, hrel)/0.95)^0.29491"/>
	<tree name="pipo_98_73.5" bhd="98" h="73.5" crown="28.96" formula="6.61*(min(0.95, hrel)/0.95)^0.29491"/>
	<tree name="pipo_99_44.55" bhd="99" h="44.55" crown="17.55" formula="6.664*(min(0.95, hrel)/0.95)^0.29491"/>
	<tree name="pipo_99_54.45" bhd="99" h="54.45" crown="21.45" formula="6.664*(min(0.95, hrel)/0.95)^0.29491"/>
	<tree name="pipo_99_64.35" bhd="99" h="64.35" crown="25.35" formula="6.664*(min(0.95, hrel)/0.95)^0.29491"/>
	<tree name="pipo_99_74.25" bhd="99" h="74.25" crown="29.25" formula="6.664*(min(0.95, hrel)/0.95)^0.29491"/>
	<tree name="pipo_100_45" bhd="100" h="45" crown="17.73" formula="6.718*(min(0.95, hrel)/0.95)^0.29491"/>
	<tree name="pipo_100_55" bhd="100" h="55" crown="21.67" formula="6.718*(min(0.95, hrel)/0.95)^0.29491"/>
	<tree name="pipo_100_65" bhd="100" h="65" crown="25.61" formula="6.718*(min(0.95, hrel)/0.95)^0.29491"/>
	<tree name="pipo_100_75" bhd="100" h="75" crown="29.55" formula="6.718*(min(0.95, hrel)/0.95)^0.29491"/>
	<tree name="pipo_101_45.45" bhd="101" h="45.45" crown="17.91" formula="6.771*(min(0.95, hrel)/0.95)^0.29491"/>
	<tree name="pipo_101_55.55" bhd="101" h="55.55" crown="21.89" formula="6.771*(min(0.95, hrel)/0.95)^0.29491"/>
	<tree name="pipo_101_65.65" bhd="101" h="65.65" crown="25.87" formula="6.771*(min(0.95, hrel)/0.95)^0.29491"/>
	<tree name="pipo_101_75.75" bhd="101" h="75.75" crown="29.85" formula="6.771*(min(0.95, hrel)/0.95)^0.29491"/>
	<tree name="pipo_102_45.9" bhd="102" h="45.9" crown="18.08" formula="6.825*(min(0.95, hrel)/0.95)^0.29491"/>
	<tree name="pipo_102_56.1" bhd="102" h="56.1" crown="22.1" formula="6.825*(min(0.95, hrel)/0.95)^0.29491"/>
	<tree name="pipo_102_66.3" bhd="102" h="66.3" crown="26.12" formula="6.825*(min(0.95, hrel)/0.95)^0.29491"/>
	<tree name="pipo_102_76.5" bhd="102" h="76.5" crown="30.14" formula="6.825*(min(0.95, hrel)/0.95)^0.29491"/>
	<tree name="pipo_103_46.35" bhd="103" h="46.35" crown="18.26" formula="6.879*(min(0.95, hrel)/0.95)^0.29491"/>
	<tree name="pipo_103_56.65" bhd="103" h="56.65" crown="22.32" formula="6.879*(min(0.95, hrel)/0.95)^0.29491"/>
	<tree name="pipo_103_66.95" bhd="103" h="66.95" crown="26.38" formula="6.879*(min(0.95, hrel)/0.95)^0.29491"/>
	<tree name="pipo_103_77.25" bhd="103" h="77.25" crown="30.44" formula="6.879*(min(0.95, hrel)/0.95)^0.29491"/>
	<tree name="pipo_104_46.8" bhd="104" h="46.8" crown="18.44" formula="6.933*(min(0.95, hrel)/0.95)^0.29491"/>
	<tree name="pipo_104_57.2" bhd="104" h="57.2" crown="22.54" formula="6.933*(min(0.95, hrel)/0.95)^0.29491"/>
	<tree name="pipo_104_67.6" bhd="104" h="67.6" crown="26.63" formula="6.933*(min(0.95, hrel)/0.95)^0.29491"/>
	<tree name="pipo_104_78" bhd="104" h="78" crown="30.73" formula="6.933*(min(0.95, hrel)/0.95)^0.29491"/>
	<tree name="pipo_105_47.25" bhd="105" h="47.25" crown="18.62" formula="6.987*(min(0.95, hrel)/0.95)^0.29491"/>
	<tree name="pipo_105_57.75" bhd="105" h="57.75" crown="22.75" formula="6.987*(min(0.95, hrel)/0.95)^0.29491"/>
	<tree name="pipo_105_68.25" bhd="105" h="68.25" crown="26.89" formula="6.987*(min(0.95, hrel)/0.95)^0.29491"/>
	<tree name="pipo_105_78.75" bhd="105" h="78.75" crown="31.03" formula="6.987*(min(0.95, hrel)/0.95)^0.29491"/>
	<tree name="pipo_106_47.7" bhd="106" h="47.7" crown="18.79" formula="7.041*(min(0.95, hrel)/0.95)^0.29491"/>
	<tree name="pipo_106_58.3" bhd="106" h="58.3" crown="22.97" formula="7.041*(min(0.95, hrel)/0.95)^0.29491"/>
	<tree name="pipo_106_68.9" bhd="106" h="68.9" crown="27.15" formula="7.041*(min(0.95, hrel)/0.95)^0.29491"/>
	<tree name="pipo_106_79.5" bhd="106" h="79.5" crown="31.32" formula="7.041*(min(0.95, hrel)/0.95)^0.29491"/>
	<tree name="pipo_107_48.15" bhd="107" h="48.15" crown="18.97" formula="7.095*(min(0.95, hrel)/0.95)^0.29491"/>
	<tree name="pipo_107_58.85" bhd="107" h="58.85" crown="23.19" formula="7.095*(min(0.95, hrel)/0.95)^0.29491"/>
	<tree name="pipo_107_69.55" bhd="107" h="69.55" crown="27.4" formula="7.095*(min(0.95, hrel)/0.95)^0.29491"/>
	<tree name="pipo_107_80.25" bhd="107" h="80.25" crown="31.62" formula="7.095*(min(0.95, hrel)/0.95)^0.29491"/>
	<tree name="pipo_108_48.6" bhd="108" h="48.6" crown="19.15" formula="7.149*(min(0.95, hrel)/0.95)^0.29491"/>
	<tree name="pipo_108_59.4" bhd="108" h="59.4" crown="23.4" formula="7.149*(min(0.95, hrel)/0.95)^0.29491"/>
	<tree name="pipo_108_70.2" bhd="108" h="70.2" crown="27.66" formula="7.149*(min(0.95, hrel)/0.95)^0.29491"/>
	<tree name="pipo_108_81" bhd="108" h="81" crown="31.91" formula="7.149*(min(0.95, hrel)/0.95)^0.29491"/>
	<tree name="pipo_109_49.05" bhd="109" h="49.05" crown="19.33" formula="7.203*(min(0.95, hrel)/0.95)^0.29491"/>
	<tree name="pipo_109_59.95" bhd="109" h="59.95" crown="23.62" formula="7.203*(min(0.95, hrel)/0.95)^0.29491"/>
	<tree name="pipo_109_70.85" bhd="109" h="70.85" crown="27.91" formula="7.203*(min(0.95, hrel)/0.95)^0.29491"/>
	<tree name="pipo_109_81.75" bhd="109" h="81.75" crown="32.21" formula="7.203*(min(0.95, hrel)/0.95)^0.29491"/>
	<tree name="pipo_110_49.5" bhd="110" h="49.5" crown="19.5" formula="7.257*(min(0.95, hrel)/0.95)^0.29491"/>
	<tree name="pipo_110_60.5" bhd="110" h="60.5" crown="23.84" formula="7.257*(min(0.95, hrel)/0.95)^0.29491"/>
	<tree name="pipo_110_71.5" bhd="110" h="71.5" crown="28.17" formula="7.257*(min(0.95, hrel)/0.95)^0.29491"/>
	<tree name="pipo_110_82.5" bhd="110" h="82.5" crown="32.51" formula="7.257*(min(0.95, hrel)/0.95)^0.29491"/>
	<tree name="pipo_111_49.95" bhd="111" h="49.95" crown="19.68" formula="7.311*(min(0.95, hrel)/0.95)^0.29491"/>
	<tree name="pipo_111_61.05" bhd="111" h="61.05" crown="24.05" formula="7.311*(min(0.95, hrel)/0.95)^0.29491"/>
	<tree name="pipo_111_72.15" bhd="111" h="72.15" crown="28.43" formula="7.311*(min(0.95, hrel)/0.95)^0.29491"/>
	<tree name="pipo_111_83.25" bhd="111" h="83.25" crown="32.8" formula="7.311*(min(0.95, hrel)/0.95)^0.29491"/>
	<tree name="pipo_112_50.4" bhd="112" h="50.4" crown="19.86" formula="7.364*(min(0.95, hrel)/0.95)^0.29491"/>
	<tree name="pipo_112_61.6" bhd="112" h="61.6" crown="24.27" formula="7.364*(min(0.95, hrel)/0.95)^0.29491"/>
	<tree name="pipo_112_72.8" bhd="112" h="72.8" crown="28.68" formula="7.364*(min(0.95, hrel)/0.95)^0.29491"/>
	<tree name="pipo_112_84" bhd="112" h="84" crown="33.1" formula="7.364*(min(0.95, hrel)/0.95)^0.29491"/>
	<tree name="pipo_113_50.85" bhd="113" h="50.85" crown="20.03" formula="7.418*(min(0.95, hrel)/0.95)^0.29491"/>
	<tree name="pipo_113_62.15" bhd="113" h="62.15" crown="24.49" formula="7.418*(min(0.95, hrel)/0.95)^0.29491"/>
	<tree name="pipo_113_73.45" bhd="113" h="73.45" crown="28.94" formula="7.418*(min(0.95, hrel)/0.95)^0.29491"/>
	<tree name="pipo_113_84.75" bhd="113" h="84.75" crown="33.39" formula="7.418*(min(0.95, hrel)/0.95)^0.29491"/>
	<tree name="pipo_114_51.3" bhd="114" h="51.3" crown="20.21" formula="7.472*(min(0.95, hrel)/0.95)^0.29491"/>
	<tree name="pipo_114_62.7" bhd="114" h="62.7" crown="24.7" formula="7.472*(min(0.95, hrel)/0.95)^0.29491"/>
	<tree name="pipo_114_74.1" bhd="114" h="74.1" crown="29.2" formula="7.472*(min(0.95, hrel)/0.95)^0.29491"/>
	<tree name="pipo_114_85.5" bhd="114" h="85.5" crown="33.69" formula="7.472*(min(0.95, hrel)/0.95)^0.29491"/>
	<tree name="pipo_115_51.75" bhd="115" h="51.75" crown="20.39" formula="7.526*(min(0.95, hrel)/0.95)^0.29491"/>
	<tree name="pipo_115_63.25" bhd="115" h="63.25" crown="24.92" formula="7.526*(min(0.95, hrel)/0.95)^0.29491"/>
	<tree name="pipo_115_74.75" bhd="115" h="74.75" crown="29.45" formula="7.526*(min(0.95, hrel)/0.95)^0.29491"/>
	<tree name="pipo_115_86.25" bhd="115" h="86.25" crown="33.98" formula="7.526*(min(0.95, hrel)/0.95)^0.29491"/>
	<tree name="pipo_116_52.2" bhd="116" h="52.2" crown="20.57" formula="7.58*(min(0.95, hrel)/0.95)^0.29491"/>
	<tree name="pipo_116_63.8" bhd="116" h="63.8" crown="25.14" formula="7.58*(min(0.95, hrel)/0.95)^0.29491"/>
	<tree name="pipo_116_75.4" bhd="116" h="75.4" crown="29.71" formula="7.58*(min(0.95, hrel)/0.95)^0.29491"/>
	<tree name="pipo_116_87" bhd="116" h="87" crown="34.28" formula="7.58*(min(0.95, hrel)/0.95)^0.29491"/>
	<tree name="pipo_117_52.65" bhd="117" h="52.65" crown="20.74" formula="7.634*(min(0.95, hrel)/0.95)^0.29491"/>
	<tree name="pipo_117_64.35" bhd="117" h="64.35" crown="25.35" formula="7.634*(min(0.95, hrel)/0.95)^0.29491"/>
	<tree name="pipo_117_76.05" bhd="117" h="76.05" crown="29.96" formula="7.634*(min(0.95, hrel)/0.95)^0.29491"/>
	<tree name="pipo_117_87.75" bhd="117" h="87.75" crown="34.57" formula="7.634*(min(0.95, hrel)/0.95)^0.29491"/>
	<tree name="pipo_118_53.1" bhd="118" h="53.1" crown="20.92" formula="7.688*(min(0.95, hrel)/0.95)^0.29491"/>
	<tree name="pipo_118_64.9" bhd="118" h="64.9" crown="25.57" formula="7.688*(min(0.95, hrel)/0.95)^0.29491"/>
	<tree name="pipo_118_76.7" bhd="118" h="76.7" crown="30.22" formula="7.688*(min(0.95, hrel)/0.95)^0.29491"/>
	<tree name="pipo_118_88.5" bhd="118" h="88.5" crown="34.87" formula="7.688*(min(0.95, hrel)/0.95)^0.29491"/>
	<tree name="pipo_119_53.55" bhd="119" h="53.55" crown="21.1" formula="7.742*(min(0.95, hrel)/0.95)^0.29491"/>
	<tree name="pipo_119_65.45" bhd="119" h="65.45" crown="25.79" formula="7.742*(min(0.95, hrel)/0.95)^0.29491"/>
	<tree name="pipo_119_77.35" bhd="119" h="77.35" crown="30.48" formula="7.742*(min(0.95, hrel)/0.95)^0.29491"/>
	<tree name="pipo_119_89.25" bhd="119" h="89.25" crown="35.16" formula="7.742*(min(0.95, hrel)/0.95)^0.29491"/>
	<tree name="pipo_120_54" bhd="120" h="54" crown="21.28" formula="7.796*(min(0.95, hrel)/0.95)^0.29491"/>
	<tree name="pipo_120_66" bhd="120" h="66" crown="26" formula="7.796*(min(0.95, hrel)/0.95)^0.29491"/>
	<tree name="pipo_120_78" bhd="120" h="78" crown="30.73" formula="7.796*(min(0.95, hrel)/0.95)^0.29491"/>
	<tree name="pipo_120_90" bhd="120" h="90" crown="35.46" formula="7.796*(min(0.95, hrel)/0.95)^0.29491"/>
	<tree name="pipo_121_54.45" bhd="121" h="54.45" crown="21.45" formula="7.85*(min(0.95, hrel)/0.95)^0.29491"/>
	<tree name="pipo_121_66.55" bhd="121" h="66.55" crown="26.22" formula="7.85*(min(0.95, hrel)/0.95)^0.29491"/>
	<tree name="pipo_121_78.65" bhd="121" h="78.65" crown="30.99" formula="7.85*(min(0.95, hrel)/0.95)^0.29491"/>
	<tree name="pipo_121_90.75" bhd="121" h="90.75" crown="35.76" formula="7.85*(min(0.95, hrel)/0.95)^0.29491"/>
	<tree name="pipo_122_54.9" bhd="122" h="54.9" crown="21.63" formula="7.904*(min(0.95, hrel)/0.95)^0.29491"/>
	<tree name="pipo_122_67.1" bhd="122" h="67.1" crown="26.44" formula="7.904*(min(0.95, hrel)/0.95)^0.29491"/>
	<tree name="pipo_122_79.3" bhd="122" h="79.3" crown="31.24" formula="7.904*(min(0.95, hrel)/0.95)^0.29491"/>
	<tree name="pipo_122_91.5" bhd="122" h="91.5" crown="36.05" formula="7.904*(min(0.95, hrel)/0.95)^0.29491"/>
	<tree name="pipo_123_55.35" bhd="123" h="55.35" crown="21.81" formula="7.957*(min(0.95, hrel)/0.95)^0.29491"/>
	<tree name="pipo_123_67.65" bhd="123" h="67.65" crown="26.65" formula="7.957*(min(0.95, hrel)/0.95)^0.29491"/>
	<tree name="pipo_123_79.95" bhd="123" h="79.95" crown="31.5" formula="7.957*(min(0.95, hrel)/0.95)^0.29491"/>
	<tree name="pipo_123_92.25" bhd="123" h="92.25" crown="36.35" formula="7.957*(min(0.95, hrel)/0.95)^0.29491"/>
	<tree name="pipo_124_55.8" bhd="124" h="55.8" crown="21.99" formula="8.011*(min(0.95, hrel)/0.95)^0.29491"/>
	<tree name="pipo_124_68.2" bhd="124" h="68.2" crown="26.87" formula="8.011*(min(0.95, hrel)/0.95)^0.29491"/>
	<tree name="pipo_124_80.6" bhd="124" h="80.6" crown="31.76" formula="8.011*(min(0.95, hrel)/0.95)^0.29491"/>
	<tree name="pipo_124_93" bhd="124" h="93" crown="36.64" formula="8.011*(min(0.95, hrel)/0.95)^0.29491"/>
	<tree name="pipo_125_56.25" bhd="125" h="56.25" crown="22.16" formula="8.065*(min(0.95, hrel)/0.95)^0.29491"/>
	<tree name="pipo_125_68.75" bhd="125" h="68.75" crown="27.09" formula="8.065*(min(0.95, hrel)/0.95)^0.29491"/>
	<tree name="pipo_125_81.25" bhd="125" h="81.25" crown="32.01" formula="8.065*(min(0.95, hrel)/0.95)^0.29491"/>
	<tree name="pipo_125_93.75" bhd="125" h="93.75" crown="36.94" formula="8.065*(min(0.95, hrel)/0.95)^0.29491"/>
	<tree name="pipo_126_56.7" bhd="126" h="56.7" crown="22.34" formula="8.119*(min(0.95, hrel)/0.95)^0.29491"/>
	<tree name="pipo_126_69.3" bhd="126" h="69.3" crown="27.3" formula="8.119*(min(0.95, hrel)/0.95)^0.29491"/>
	<tree name="pipo_126_81.9" bhd="126" h="81.9" crown="32.27" formula="8.119*(min(0.95, hrel)/0.95)^0.29491"/>
	<tree name="pipo_126_94.5" bhd="126" h="94.5" crown="37.23" formula="8.119*(min(0.95, hrel)/0.95)^0.29491"/>
	<tree name="pipo_127_57.15" bhd="127" h="57.15" crown="22.52" formula="8.173*(min(0.95, hrel)/0.95)^0.29491"/>
	<tree name="pipo_127_69.85" bhd="127" h="69.85" crown="27.52" formula="8.173*(min(0.95, hrel)/0.95)^0.29491"/>
	<tree name="pipo_127_82.55" bhd="127" h="82.55" crown="32.52" formula="8.173*(min(0.95, hrel)/0.95)^0.29491"/>
	<tree name="pipo_127_95.25" bhd="127" h="95.25" crown="37.53" formula="8.173*(min(0.95, hrel)/0.95)^0.29491"/>
	<tree name="pipo_128_57.6" bhd="128" h="57.6" crown="22.69" formula="8.227*(min(0.95, hrel)/0.95)^0.29491"/>
	<tree name="pipo_128_70.4" bhd="128" h="70.4" crown="27.74" formula="8.227*(min(0.95, hrel)/0.95)^0.29491"/>
	<tree name="pipo_128_83.2" bhd="128" h="83.2" crown="32.78" formula="8.227*(min(0.95, hrel)/0.95)^0.29491"/>
	<tree name="pipo_129_58.05" bhd="129" h="58.05" crown="22.87" formula="8.281*(min(0.95, hrel)/0.95)^0.29491"/>
	<tree name="pipo_129_70.95" bhd="129" h="70.95" crown="27.95" formula="8.281*(min(0.95, hrel)/0.95)^0.29491"/>
	<tree name="pipo_129_83.85" bhd="129" h="83.85" crown="33.04" formula="8.281*(min(0.95, hrel)/0.95)^0.29491"/>
	<tree name="pipo_130_58.5" bhd="130" h="58.5" crown="23.05" formula="8.335*(min(0.95, hrel)/0.95)^0.29491"/>
	<tree name="pipo_130_71.5" bhd="130" h="71.5" crown="28.17" formula="8.335*(min(0.95, hrel)/0.95)^0.29491"/>
	<tree name="pipo_130_84.5" bhd="130" h="84.5" crown="33.29" formula="8.335*(min(0.95, hrel)/0.95)^0.29491"/>
	<tree name="pipo_131_58.95" bhd="131" h="58.95" crown="23.23" formula="8.389*(min(0.95, hrel)/0.95)^0.29491"/>
	<tree name="pipo_131_72.05" bhd="131" h="72.05" crown="28.39" formula="8.389*(min(0.95, hrel)/0.95)^0.29491"/>
	<tree name="pipo_131_85.15" bhd="131" h="85.15" crown="33.55" formula="8.389*(min(0.95, hrel)/0.95)^0.29491"/>
	<tree name="pipo_132_59.4" bhd="132" h="59.4" crown="23.4" formula="8.443*(min(0.95, hrel)/0.95)^0.29491"/>
	<tree name="pipo_132_72.6" bhd="132" h="72.6" crown="28.6" formula="8.443*(min(0.95, hrel)/0.95)^0.29491"/>
	<tree name="pipo_132_85.8" bhd="132" h="85.8" crown="33.81" formula="8.443*(min(0.95, hrel)/0.95)^0.29491"/>
	<tree name="pipo_133_59.85" bhd="133" h="59.85" crown="23.58" formula="8.497*(min(0.95, hrel)/0.95)^0.29491"/>
	<tree name="pipo_133_73.15" bhd="133" h="73.15" crown="28.82" formula="8.497*(min(0.95, hrel)/0.95)^0.29491"/>
	<tree name="pipo_133_86.45" bhd="133" h="86.45" crown="34.06" formula="8.497*(min(0.95, hrel)/0.95)^0.29491"/>
	<tree name="pipo_134_60.3" bhd="134" h="60.3" crown="23.76" formula="8.55*(min(0.95, hrel)/0.95)^0.29491"/>
	<tree name="pipo_134_73.7" bhd="134" h="73.7" crown="29.04" formula="8.55*(min(0.95, hrel)/0.95)^0.29491"/>
	<tree name="pipo_134_87.1" bhd="134" h="87.1" crown="34.32" formula="8.55*(min(0.95, hrel)/0.95)^0.29491"/>
	<tree name="pipo_135_60.75" bhd="135" h="60.75" crown="23.94" formula="8.604*(min(0.95, hrel)/0.95)^0.29491"/>
	<tree name="pipo_135_74.25" bhd="135" h="74.25" crown="29.25" formula="8.604*(min(0.95, hrel)/0.95)^0.29491"/>
	<tree name="pipo_135_87.75" bhd="135" h="87.75" crown="34.57" formula="8.604*(min(0.95, hrel)/0.95)^0.29491"/>
	<tree name="pipo_136_61.2" bhd="136" h="61.2" crown="24.11" formula="8.658*(min(0.95, hrel)/0.95)^0.29491"/>
	<tree name="pipo_136_74.8" bhd="136" h="74.8" crown="29.47" formula="8.658*(min(0.95, hrel)/0.95)^0.29491"/>
	<tree name="pipo_136_88.4" bhd="136" h="88.4" crown="34.83" formula="8.658*(min(0.95, hrel)/0.95)^0.29491"/>
	<tree name="pipo_137_61.65" bhd="137" h="61.65" crown="24.29" formula="8.712*(min(0.95, hrel)/0.95)^0.29491"/>
	<tree name="pipo_137_75.35" bhd="137" h="75.35" crown="29.69" formula="8.712*(min(0.95, hrel)/0.95)^0.29491"/>
	<tree name="pipo_137_89.05" bhd="137" h="89.05" crown="35.09" formula="8.712*(min(0.95, hrel)/0.95)^0.29491"/>
	<tree name="pipo_138_62.1" bhd="138" h="62.1" crown="24.47" formula="8.766*(min(0.95, hrel)/0.95)^0.29491"/>
	<tree name="pipo_138_75.9" bhd="138" h="75.9" crown="29.9" formula="8.766*(min(0.95, hrel)/0.95)^0.29491"/>
	<tree name="pipo_138_89.7" bhd="138" h="89.7" crown="35.34" formula="8.766*(min(0.95, hrel)/0.95)^0.29491"/>
	<tree name="pipo_139_62.55" bhd="139" h="62.55" crown="24.64" formula="8.82*(min(0.95, hrel)/0.95)^0.29491"/>
	<tree name="pipo_139_76.45" bhd="139" h="76.45" crown="30.12" formula="8.82*(min(0.95, hrel)/0.95)^0.29491"/>
	<tree name="pipo_139_90.35" bhd="139" h="90.35" crown="35.6" formula="8.82*(min(0.95, hrel)/0.95)^0.29491"/>
	<tree name="pipo_140_63" bhd="140" h="63" crown="24.82" formula="8.874*(min(0.95, hrel)/0.95)^0.29491"/>
	<tree name="pipo_140_77" bhd="140" h="77" crown="30.34" formula="8.874*(min(0.95, hrel)/0.95)^0.29491"/>
	<tree name="pipo_140_91" bhd="140" h="91" crown="35.85" formula="8.874*(min(0.95, hrel)/0.95)^0.29491"/>
	<tree name="pipo_141_63.45" bhd="141" h="63.45" crown="25" formula="8.928*(min(0.95, hrel)/0.95)^0.29491"/>
	<tree name="pipo_141_77.55" bhd="141" h="77.55" crown="30.55" formula="8.928*(min(0.95, hrel)/0.95)^0.29491"/>
	<tree name="pipo_141_91.65" bhd="141" h="91.65" crown="36.11" formula="8.928*(min(0.95, hrel)/0.95)^0.29491"/>
	<tree name="pipo_142_63.9" bhd="142" h="63.9" crown="25.18" formula="8.982*(min(0.95, hrel)/0.95)^0.29491"/>
	<tree name="pipo_142_78.1" bhd="142" h="78.1" crown="30.77" formula="8.982*(min(0.95, hrel)/0.95)^0.29491"/>
	<tree name="pipo_142_92.3" bhd="142" h="92.3" crown="36.37" formula="8.982*(min(0.95, hrel)/0.95)^0.29491"/>
	<tree name="pipo_143_64.35" bhd="143" h="64.35" crown="25.35" formula="9.036*(min(0.95, hrel)/0.95)^0.29491"/>
	<tree name="pipo_143_78.65" bhd="143" h="78.65" crown="30.99" formula="9.036*(min(0.95, hrel)/0.95)^0.29491"/>
	<tree name="pipo_143_92.95" bhd="143" h="92.95" crown="36.62" formula="9.036*(min(0.95, hrel)/0.95)^0.29491"/>
	<tree name="pipo_144_64.8" bhd="144" h="64.8" crown="25.53" formula="9.09*(min(0.95, hrel)/0.95)^0.29491"/>
	<tree name="pipo_144_79.2" bhd="144" h="79.2" crown="31.2" formula="9.09*(min(0.95, hrel)/0.95)^0.29491"/>
	<tree name="pipo_144_93.6" bhd="144" h="93.6" crown="36.88" formula="9.09*(min(0.95, hrel)/0.95)^0.29491"/>
	<tree name="pipo_145_65.25" bhd="145" h="65.25" crown="25.71" formula="9.143*(min(0.95, hrel)/0.95)^0.29491"/>
	<tree name="pipo_145_79.75" bhd="145" h="79.75" crown="31.42" formula="9.143*(min(0.95, hrel)/0.95)^0.29491"/>
	<tree name="pipo_145_94.25" bhd="145" h="94.25" crown="37.13" formula="9.143*(min(0.95, hrel)/0.95)^0.29491"/>
	<tree name="pipo_146_65.7" bhd="146" h="65.7" crown="25.89" formula="9.197*(min(0.95, hrel)/0.95)^0.29491"/>
	<tree name="pipo_146_80.3" bhd="146" h="80.3" crown="31.64" formula="9.197*(min(0.95, hrel)/0.95)^0.29491"/>
	<tree name="pipo_146_94.9" bhd="146" h="94.9" crown="37.39" formula="9.197*(min(0.95, hrel)/0.95)^0.29491"/>
	<tree name="pipo_147_66.15" bhd="147" h="66.15" crown="26.06" formula="9.251*(min(0.95, hrel)/0.95)^0.29491"/>
	<tree name="pipo_147_80.85" bhd="147" h="80.85" crown="31.85" formula="9.251*(min(0.95, hrel)/0.95)^0.29491"/>
	<tree name="pipo_147_95.55" bhd="147" h="95.55" crown="37.65" formula="9.251*(min(0.95, hrel)/0.95)^0.29491"/>
	<tree name="pipo_148_66.6" bhd="148" h="66.6" crown="26.24" formula="9.305*(min(0.95, hrel)/0.95)^0.29491"/>
	<tree name="pipo_148_81.4" bhd="148" h="81.4" crown="32.07" formula="9.305*(min(0.95, hrel)/0.95)^0.29491"/>
	<tree name="pipo_148_96.2" bhd="148" h="96.2" crown="37.9" formula="9.305*(min(0.95, hrel)/0.95)^0.29491"/>
	<tree name="pipo_149_67.05" bhd="149" h="67.05" crown="26.42" formula="9.359*(min(0.95, hrel)/0.95)^0.29491"/>
	<tree name="pipo_149_81.95" bhd="149" h="81.95" crown="32.29" formula="9.359*(min(0.95, hrel)/0.95)^0.29491"/>
	<tree name="pipo_149_96.85" bhd="149" h="96.85" crown="38.16" formula="9.359*(min(0.95, hrel)/0.95)^0.29491"/>
	<tree name="pipo_150_67.5" bhd="150" h="67.5" crown="26.6" formula="9.413*(min(0.95, hrel)/0.95)^0.29491"/>
	<tree name="pipo_150_82.5" bhd="150" h="82.5" crown="32.51" formula="9.413*(min(0.95, hrel)/0.95)^0.29491"/>
	<tree name="pipo_150_97.5" bhd="150" h="97.5" crown="38.42" formula="9.413*(min(0.95, hrel)/0.95)^0.29491"/>
	<tree name="pipo_151_67.95" bhd="151" h="67.95" crown="26.77" formula="9.467*(min(0.95, hrel)/0.95)^0.29491"/>
	<tree name="pipo_151_83.05" bhd="151" h="83.05" crown="32.72" formula="9.467*(min(0.95, hrel)/0.95)^0.29491"/>
	<tree name="pipo_151_98.15" bhd="151" h="98.15" crown="38.67" formula="9.467*(min(0.95, hrel)/0.95)^0.29491"/>
	<tree name="pipo_152_68.4" bhd="152" h="68.4" crown="26.95" formula="9.521*(min(0.95, hrel)/0.95)^0.29491"/>
	<tree name="pipo_152_83.6" bhd="152" h="83.6" crown="32.94" formula="9.521*(min(0.95, hrel)/0.95)^0.29491"/>
	<tree name="pipo_152_98.8" bhd="152" h="98.8" crown="38.93" formula="9.521*(min(0.95, hrel)/0.95)^0.29491"/>
	<tree name="pipo_153_68.85" bhd="153" h="68.85" crown="27.13" formula="9.575*(min(0.95, hrel)/0.95)^0.29491"/>
	<tree name="pipo_153_84.15" bhd="153" h="84.15" crown="33.16" formula="9.575*(min(0.95, hrel)/0.95)^0.29491"/>
	<tree name="pipo_153_99.45" bhd="153" h="99.45" crown="39.18" formula="9.575*(min(0.95, hrel)/0.95)^0.29491"/>
	<tree name="pipo_154_69.3" bhd="154" h="69.3" crown="27.3" formula="9.629*(min(0.95, hrel)/0.95)^0.29491"/>
	<tree name="pipo_154_84.7" bhd="154" h="84.7" crown="33.37" formula="9.629*(min(0.95, hrel)/0.95)^0.29491"/>
	<tree name="pipo_154_100.1" bhd="154" h="100.1" crown="39.44" formula="9.629*(min(0.95, hrel)/0.95)^0.29491"/>
	<tree name="pipo_155_69.75" bhd="155" h="69.75" crown="27.48" formula="9.683*(min(0.95, hrel)/0.95)^0.29491"/>
	<tree name="pipo_155_85.25" bhd="155" h="85.25" crown="33.59" formula="9.683*(min(0.95, hrel)/0.95)^0.29491"/>
	<tree name="pipo_155_100.75" bhd="155" h="100.75" crown="39.7" formula="9.683*(min(0.95, hrel)/0.95)^0.29491"/>
	<tree name="pipo_156_70.2" bhd="156" h="70.2" crown="27.66" formula="9.736*(min(0.95, hrel)/0.95)^0.29491"/>
	<tree name="pipo_156_85.8" bhd="156" h="85.8" crown="33.81" formula="9.736*(min(0.95, hrel)/0.95)^0.29491"/>
	<tree name="pipo_156_101.4" bhd="156" h="101.4" crown="39.95" formula="9.736*(min(0.95, hrel)/0.95)^0.29491"/>
	<tree name="pipo_157_70.65" bhd="157" h="70.65" crown="27.84" formula="9.79*(min(0.95, hrel)/0.95)^0.29491"/>
	<tree name="pipo_157_86.35" bhd="157" h="86.35" crown="34.02" formula="9.79*(min(0.95, hrel)/0.95)^0.29491"/>
	<tree name="pipo_157_102.05" bhd="157" h="102.05" crown="40.21" formula="9.79*(min(0.95, hrel)/0.95)^0.29491"/>
	<tree name="pipo_158_71.1" bhd="158" h="71.1" crown="28.01" formula="9.844*(min(0.95, hrel)/0.95)^0.29491"/>
	<tree name="pipo_158_86.9" bhd="158" h="86.9" crown="34.24" formula="9.844*(min(0.95, hrel)/0.95)^0.29491"/>
	<tree name="pipo_158_102.7" bhd="158" h="102.7" crown="40.46" formula="9.844*(min(0.95, hrel)/0.95)^0.29491"/>
	<tree name="pipo_159_71.55" bhd="159" h="71.55" crown="28.19" formula="9.898*(min(0.95, hrel)/0.95)^0.29491"/>
	<tree name="pipo_159_87.45" bhd="159" h="87.45" crown="34.46" formula="9.898*(min(0.95, hrel)/0.95)^0.29491"/>
	<tree name="pipo_159_103.35" bhd="159" h="103.35" crown="40.72" formula="9.898*(min(0.95, hrel)/0.95)^0.29491"/>
	<tree name="pipo_160_72" bhd="160" h="72" crown="28.37" formula="9.952*(min(0.95, hrel)/0.95)^0.29491"/>
	<tree name="pipo_160_88" bhd="160" h="88" crown="34.67" formula="9.952*(min(0.95, hrel)/0.95)^0.29491"/>
	<tree name="pipo_160_104" bhd="160" h="104" crown="40.98" formula="9.952*(min(0.95, hrel)/0.95)^0.29491"/>
	<tree name="pipo_161_72.45" bhd="161" h="72.45" crown="28.55" formula="10.006*(min(0.95, hrel)/0.95)^0.29491"/>
	<tree name="pipo_161_88.55" bhd="161" h="88.55" crown="34.89" formula="10.006*(min(0.95, hrel)/0.95)^0.29491"/>
	<tree name="pipo_161_104.65" bhd="161" h="104.65" crown="41.23" formula="10.006*(min(0.95, hrel)/0.95)^0.29491"/>
	<tree name="pipo_162_72.9" bhd="162" h="72.9" crown="28.72" formula="10.06*(min(0.95, hrel)/0.95)^0.29491"/>
	<tree name="pipo_162_89.1" bhd="162" h="89.1" crown="35.11" formula="10.06*(min(0.95, hrel)/0.95)^0.29491"/>
	<tree name="pipo_162_105.3" bhd="162" h="105.3" crown="41.49" formula="10.06*(min(0.95, hrel)/0.95)^0.29491"/>
	<tree name="pipo_163_73.35" bhd="163" h="73.35" crown="28.9" formula="10.114*(min(0.95, hrel)/0.95)^0.29491"/>
	<tree name="pipo_163_89.65" bhd="163" h="89.65" crown="35.32" formula="10.114*(min(0.95, hrel)/0.95)^0.29491"/>
	<tree name="pipo_163_105.95" bhd="163" h="105.95" crown="41.74" formula="10.114*(min(0.95, hrel)/0.95)^0.29491"/>
	<tree name="pipo_164_73.8" bhd="164" h="73.8" crown="29.08" formula="10.168*(min(0.95, hrel)/0.95)^0.29491"/>
	<tree name="pipo_164_90.2" bhd="164" h="90.2" crown="35.54" formula="10.168*(min(0.95, hrel)/0.95)^0.29491"/>
	<tree name="pipo_164_106.6" bhd="164" h="106.6" crown="42" formula="10.168*(min(0.95, hrel)/0.95)^0.29491"/>
	<tree name="pipo_165_74.25" bhd="165" h="74.25" crown="29.25" formula="10.222*(min(0.95, hrel)/0.95)^0.29491"/>
	<tree name="pipo_165_90.75" bhd="165" h="90.75" crown="35.76" formula="10.222*(min(0.95, hrel)/0.95)^0.29491"/>
	<tree name="pipo_165_107.25" bhd="165" h="107.25" crown="42.26" formula="10.222*(min(0.95, hrel)/0.95)^0.29491"/>
	<tree name="pipo_166_74.7" bhd="166" h="74.7" crown="29.43" formula="10.276*(min(0.95, hrel)/0.95)^0.29491"/>
	<tree name="pipo_166_91.3" bhd="166" h="91.3" crown="35.97" formula="10.276*(min(0.95, hrel)/0.95)^0.29491"/>
	<tree name="pipo_166_107.9" bhd="166" h="107.9" crown="42.51" formula="10.276*(min(0.95, hrel)/0.95)^0.29491"/>
	<tree name="pipo_167_75.15" bhd="167" h="75.15" crown="29.61" formula="10.33*(min(0.95, hrel)/0.95)^0.29491"/>
	<tree name="pipo_167_91.85" bhd="167" h="91.85" crown="36.19" formula="10.33*(min(0.95, hrel)/0.95)^0.29491"/>
	<tree name="pipo_167_108.55" bhd="167" h="108.55" crown="42.77" formula="10.33*(min(0.95, hrel)/0.95)^0.29491"/>
	<tree name="pipo_168_75.6" bhd="168" h="75.6" crown="29.79" formula="10.383*(min(0.95, hrel)/0.95)^0.29491"/>
	<tree name="pipo_168_92.4" bhd="168" h="92.4" crown="36.41" formula="10.383*(min(0.95, hrel)/0.95)^0.29491"/>
	<tree name="pipo_168_109.2" bhd="168" h="109.2" crown="43.02" formula="10.383*(min(0.95, hrel)/0.95)^0.29491"/>
	<tree name="pipo_169_76.05" bhd="169" h="76.05" crown="29.96" formula="10.437*(min(0.95, hrel)/0.95)^0.29491"/>
	<tree name="pipo_169_92.95" bhd="169" h="92.95" crown="36.62" formula="10.437*(min(0.95, hrel)/0.95)^0.29491"/>
	<tree name="pipo_169_109.85" bhd="169" h="109.85" crown="43.28" formula="10.437*(min(0.95, hrel)/0.95)^0.29491"/>
	<tree name="pipo_170_76.5" bhd="170" h="76.5" crown="30.14" formula="10.491*(min(0.95, hrel)/0.95)^0.29491"/>
	<tree name="pipo_170_93.5" bhd="170" h="93.5" crown="36.84" formula="10.491*(min(0.95, hrel)/0.95)^0.29491"/>
	<tree name="pipo_170_110.5" bhd="170" h="110.5" crown="43.54" formula="10.491*(min(0.95, hrel)/0.95)^0.29491"/>
	<tree name="pipo_171_76.95" bhd="171" h="76.95" crown="30.32" formula="10.545*(min(0.95, hrel)/0.95)^0.29491"/>
	<tree name="pipo_171_94.05" bhd="171" h="94.05" crown="37.06" formula="10.545*(min(0.95, hrel)/0.95)^0.29491"/>
	<tree name="pipo_171_111.15" bhd="171" h="111.15" crown="43.79" formula="10.545*(min(0.95, hrel)/0.95)^0.29491"/>
	<tree name="pipo_172_77.4" bhd="172" h="77.4" crown="30.5" formula="10.599*(min(0.95, hrel)/0.95)^0.29491"/>
	<tree name="pipo_172_94.6" bhd="172" h="94.6" crown="37.27" formula="10.599*(min(0.95, hrel)/0.95)^0.29491"/>
	<tree name="pipo_172_111.8" bhd="172" h="111.8" crown="44.05" formula="10.599*(min(0.95, hrel)/0.95)^0.29491"/>
	<tree name="pipo_173_77.85" bhd="173" h="77.85" crown="30.67" formula="10.653*(min(0.95, hrel)/0.95)^0.29491"/>
	<tree name="pipo_173_95.15" bhd="173" h="95.15" crown="37.49" formula="10.653*(min(0.95, hrel)/0.95)^0.29491"/>
	<tree name="pipo_173_112.45" bhd="173" h="112.45" crown="44.31" formula="10.653*(min(0.95, hrel)/0.95)^0.29491"/>
	<tree name="pipo_174_78.3" bhd="174" h="78.3" crown="30.85" formula="10.707*(min(0.95, hrel)/0.95)^0.29491"/>
	<tree name="pipo_174_95.7" bhd="174" h="95.7" crown="37.71" formula="10.707*(min(0.95, hrel)/0.95)^0.29491"/>
	<tree name="pipo_174_113.1" bhd="174" h="113.1" crown="44.56" formula="10.707*(min(0.95, hrel)/0.95)^0.29491"/>
	<tree name="pipo_175_78.75" bhd="175" h="78.75" crown="31.03" formula="10.761*(min(0.95, hrel)/0.95)^0.29491"/>
	<tree name="pipo_175_96.25" bhd="175" h="96.25" crown="37.92" formula="10.761*(min(0.95, hrel)/0.95)^0.29491"/>
	<tree name="pipo_175_113.75" bhd="175" h="113.75" crown="44.82" formula="10.761*(min(0.95, hrel)/0.95)^0.29491"/>
     </trees>
</lightroom>